Workbook

Sheet README
B2: Review Engine
B3: ShelfMark's 29 checks as a standing rubric for any store · index of 21 benchmark stores + 3 reviewed targets · 2026-09-28 · Mousa Batarseh
B5: What this is | C5: The spreadsheet behind every store review I send with an application. One rubric (29 public-page checks, 5 pillars, 0–100 score) scores any storefront in about an hour; the ShelfMark index of 21 Michigan stores is the comparison pool, so each target gets a rank, not just a number; and every role-specific finding is filed in a library that the next review reuses.
B6: How a score is built | C6: Each check is 2 (meets), 1 (partly), 0 (fails) or U (unverified from public pages). Pillar % = verified points ÷ (2 × verified checks). Score = weighted average of pillar % (weights on Rubric: Findability 25, Catalog 30, Buy 20, Trust 15, Content 10). U never counts for or against a store; Coverage and Confidence show how much was observable. Identical to the ShelfMark workbook, so scores are comparable.
B7: Sheets | C7: Rubric — pillars, weights, thresholds, the 29 checks and the published reference behind each one. Index — every store scored, benchmark and targets together (targets shaded blue), with live formulas. Checks — 29 observations per store with dated evidence; the only place scores are typed. Findings — the library: strengths, fixes and role-specific findings with counts, the duty they map to, the fix and the evidence file. Impact ledger — my own outcomes with source and confidence, the single source of truth for résumé bullets. Outreach — one row per person contacted, with status and follow-up dates. Messages — the notes that go with a review.
B8: The one-hour review | C8: 1) Paste the target's homepage, robots.txt, sitemap, one category and two product URLs into the audit brief (audit-brief.md). 2) Score the 29 checks with evidence into targets/<slug>/audit.json. 3) Read the posting; find 4–6 findings that can be COUNTED across sampled pages and map each to a duty in the posting. 4) python3 build_workbook.py && python3 build_review.py <slug> — the scorecard, rank, workbook and review page are generated. 5) Write the working fixes (prototypes) by hand in the company's look. 6) Send: application link + one finding to one named person within 48 hours; log the row on Outreach.
B9: Rules | C9: Public pages only; never log in, cart or submit forms. Count things (14 of 20), never characterize ("many"). Lead with three strengths. Every finding names the page, the count, the duty it maps to and the fix. No claims about health, legal or financial language. Review pages are noindex and sent as private links to one person.
B10: Legend | C10: Blue text on yellow = typed inputs (scores, contacts, statuses). Black = formulas. Green = pulled from another sheet. Blue-shaded rows on Index = reviewed targets (not part of the public benchmark).
B11: Author | C11: Mousa Batarseh · hireme@mousabatarseh.com · mousabatarseh.com · linkedin.com/in/mousabatarseh

Sheet Index
A1: Rank (all) | B1: Rank on the benchmark | C1: Store | D1: Source | E1: Segment | F1: Platform | G1: HQ | H1: URL | I1: Audited | J1: Findability % | K1: F n | L1: Catalog % | M1: C n | N1: Buy % | O1: B n | P1: Trust % | Q1: T n | R1: Content % | S1: N n | T1: Verified (of 29) | U1: Coverage | V1: Confidence | W1: Score | X1: Grade | Y1: Band | Z1: Weakest pillar | AA1: Review page | AB1: Notes
A2: =IF(W2="","",RANK(W2,$W$2:$W$25,0)) -> 2 | B2: =IF(W2="","",1+COUNTIFS($D$2:$D$25,"Benchmark",$W$2:$W$25,">"&W2)) -> 1 | C2: Stormy Kromer | D2: Benchmark | E2: Brand & maker | F2: BigCommerce | G2: Ironwood, MI | H2: https://www.stormykromer.com | I2: 2026-09-28 | J2: =IFERROR(SUMIFS(Checks!$F$2:$F$1297,Checks!$A$2:$A$1297,$C2,Checks!$C$2:$C$1297,"F")/(2*COUNTIFS(Checks!$A$2:$A$1297,$C2,Checks!$C$2:$C$1297,"F",Checks!$F$2:$F$1297,">=0")),"") -> 0.9375 | K2: =COUNTIFS(Checks!$A$2:$A$1297,$C2,Checks!$C$2:$C$1297,"F",Checks!$F$2:$F$1297,">=0") -> 8 | L2: =IFERROR(SUMIFS(Checks!$F$2:$F$1297,Checks!$A$2:$A$1297,$C2,Checks!$C$2:$C$1297,"C")/(2*COUNTIFS(Checks!$A$2:$A$1297,$C2,Checks!$C$2:$C$1297,"C",Checks!$F$2:$F$1297,">=0")),"") -> 1 | M2: =COUNTIFS(Checks!$A$2:$A$1297,$C2,Checks!$C$2:$C$1297,"C",Checks!$F$2:$F$1297,">=0") -> 8 | N2: =IFERROR(SUMIFS(Checks!$F$2:$F$1297,Checks!$A$2:$A$1297,$C2,Checks!$C$2:$C$1297,"B")/(2*COUNTIFS(Checks!$A$2:$A$1297,$C2,Checks!$C$2:$C$1297,"B",Checks!$F$2:$F$1297,">=0")),"") -> 1 | O2: =COUNTIFS(Checks!$A$2:$A$1297,$C2,Checks!$C$2:$C$1297,"B",Checks!$F$2:$F$1297,">=0") -> 4 | P2: =IFERROR(SUMIFS(Checks!$F$2:$F$1297,Checks!$A$2:$A$1297,$C2,Checks!$C$2:$C$1297,"T")/(2*COUNTIFS(Checks!$A$2:$A$1297,$C2,Checks!$C$2:$C$1297,"T",Checks!$F$2:$F$1297,">=0")),"") -> 1 | Q2: =COUNTIFS(Checks!$A$2:$A$1297,$C2,Checks!$C$2:$C$1297,"T",Checks!$F$2:$F$1297,">=0") -> 5 | R2: =IFERROR(SUMIFS(Checks!$F$2:$F$1297,Checks!$A$2:$A$1297,$C2,Checks!$C$2:$C$1297,"N")/(2*COUNTIFS(Checks!$A$2:$A$1297,$C2,Checks!$C$2:$C$1297,"N",Checks!$F$2:$F$1297,">=0")),"") -> 0.66666667 | S2: =COUNTIFS(Checks!$A$2:$A$1297,$C2,Checks!$C$2:$C$1297,"N",Checks!$F$2:$F$1297,">=0") -> 3 | T2: =K2+M2+O2+Q2+S2 -> 28 | U2: =T2/29 -> 0.96551724 | V2: =IF(T2>=26,"High",IF(T2>=20,"Medium","Low")) -> High | W2: =IF((IF(K2>0,Rubric!$C$3,0)+IF(M2>0,Rubric!$C$4,0)+IF(O2>0,Rubric!$C$5,0)+IF(Q2>0,Rubric!$C$6,0)+IF(S2>0,Rubric!$C$7,0))=0,"",ROUND(100*(IF(K2>0,Rubric!$C$3*J2,0)+IF(M2>0,Rubric!$C$4*L2,0)+IF(O2>0,Rubric!$C$5*N2,0)+IF(Q2>0,Rubric!$C$6*P2,0)+IF(S2>0,Rubric!$C$7*R2,0))/(IF(K2>0,Rubric!$C$3,0)+IF(M2>0,Rubric!$C$4,0)+IF(O2>0,Rubric!$C$5,0)+IF(Q2>0,Rubric!$C$6,0)+IF(S2>0,Rubric!$C$7,0)),1)) -> 95.1 | X2: =IF(W2="","",IF(W2>=Rubric!$C$11,"A",IF(W2>=Rubric!$C$12,"B",IF(W2>=Rubric!$C$13,"C",IF(W2>=Rubric!$C$14,"D","F"))))) -> A | Y2: =IF(X2="","",IF(X2="A","Benchmark",IF(X2="B","Strong",IF(X2="C","Developing",IF(X2="D","Needs work","At risk"))))) -> Benchmark | Z2: =IF(COUNT(J2,L2,N2,P2,R2)=0,"",INDEX({"Findability","Catalog","Buy","Trust","Content"},MATCH(MIN(J2,L2,N2,P2,R2),CHOOSE({1,2,3,4,5},J2,L2,N2,P2,R2),0))) -> Content | AB2: Footer X/Twitter link points to twitter.com/i/flow/login?redirect_after_login=%2FStormyKromer rather than the profile URL. Category facet lists are collapsed in fetched HTML ('No filters applied'); facets confirmed on the search results page. robots.txt blocks GPTBot entirely while allowing OAI-SearchBot.
A3: =IF(W3="","",RANK(W3,$W$2:$W$25,0)) -> 3 | B3: =IF(W3="","",1+COUNTIFS($D$2:$D$25,"Benchmark",$W$2:$W$25,">"&W3)) -> 2 | C3: Gardner-White Furniture | D3: Benchmark | E3: Retail chain | F3: Custom | G3: Auburn Hills, MI | H3: https://www.gardner-white.com | I3: 2026-09-28 | J3: =IFERROR(SUMIFS(Checks!$F$2:$F$1297,Checks!$A$2:$A$1297,$C3,Checks!$C$2:$C$1297,"F")/(2*COUNTIFS(Checks!$A$2:$A$1297,$C3,Checks!$C$2:$C$1297,"F",Checks!$F$2:$F$1297,">=0")),"") -> 0.92857143 | K3: =COUNTIFS(Checks!$A$2:$A$1297,$C3,Checks!$C$2:$C$1297,"F",Checks!$F$2:$F$1297,">=0") -> 7 | L3: =IFERROR(SUMIFS(Checks!$F$2:$F$1297,Checks!$A$2:$A$1297,$C3,Checks!$C$2:$C$1297,"C")/(2*COUNTIFS(Checks!$A$2:$A$1297,$C3,Checks!$C$2:$C$1297,"C",Checks!$F$2:$F$1297,">=0")),"") -> 0.91666667 | M3: =COUNTIFS(Checks!$A$2:$A$1297,$C3,Checks!$C$2:$C$1297,"C",Checks!$F$2:$F$1297,">=0") -> 6 | N3: =IFERROR(SUMIFS(Checks!$F$2:$F$1297,Checks!$A$2:$A$1297,$C3,Checks!$C$2:$C$1297,"B")/(2*COUNTIFS(Checks!$A$2:$A$1297,$C3,Checks!$C$2:$C$1297,"B",Checks!$F$2:$F$1297,">=0")),"") -> 1 | O3: =COUNTIFS(Checks!$A$2:$A$1297,$C3,Checks!$C$2:$C$1297,"B",Checks!$F$2:$F$1297,">=0") -> 3 | P3: =IFERROR(SUMIFS(Checks!$F$2:$F$1297,Checks!$A$2:$A$1297,$C3,Checks!$C$2:$C$1297,"T")/(2*COUNTIFS(Checks!$A$2:$A$1297,$C3,Checks!$C$2:$C$1297,"T",Checks!$F$2:$F$1297,">=0")),"") -> 0.875 | Q3: =COUNTIFS(Checks!$A$2:$A$1297,$C3,Checks!$C$2:$C$1297,"T",Checks!$F$2:$F$1297,">=0") -> 4 | R3: =IFERROR(SUMIFS(Checks!$F$2:$F$1297,Checks!$A$2:$A$1297,$C3,Checks!$C$2:$C$1297,"N")/(2*COUNTIFS(Checks!$A$2:$A$1297,$C3,Checks!$C$2:$C$1297,"N",Checks!$F$2:$F$1297,">=0")),"") -> 1 | S3: =COUNTIFS(Checks!$A$2:$A$1297,$C3,Checks!$C$2:$C$1297,"N",Checks!$F$2:$F$1297,">=0") -> 3 | T3: =K3+M3+O3+Q3+S3 -> 23 | U3: =T3/29 -> 0.79310345 | V3: =IF(T3>=26,"High",IF(T3>=20,"Medium","Low")) -> Medium | W3: =IF((IF(K3>0,Rubric!$C$3,0)+IF(M3>0,Rubric!$C$4,0)+IF(O3>0,Rubric!$C$5,0)+IF(Q3>0,Rubric!$C$6,0)+IF(S3>0,Rubric!$C$7,0))=0,"",ROUND(100*(IF(K3>0,Rubric!$C$3*J3,0)+IF(M3>0,Rubric!$C$4*L3,0)+IF(O3>0,Rubric!$C$5*N3,0)+IF(Q3>0,Rubric!$C$6*P3,0)+IF(S3>0,Rubric!$C$7*R3,0))/(IF(K3>0,Rubric!$C$3,0)+IF(M3>0,Rubric!$C$4,0)+IF(O3>0,Rubric!$C$5,0)+IF(Q3>0,Rubric!$C$6,0)+IF(S3>0,Rubric!$C$7,0)),1)) -> 93.8 | X3: =IF(W3="","",IF(W3>=Rubric!$C$11,"A",IF(W3>=Rubric!$C$12,"B",IF(W3>=Rubric!$C$13,"C",IF(W3>=Rubric!$C$14,"D","F"))))) -> A | Y3: =IF(X3="","",IF(X3="A","Benchmark",IF(X3="B","Strong",IF(X3="C","Developing",IF(X3="D","Needs work","At risk"))))) -> Benchmark | Z3: =IF(COUNT(J3,L3,N3,P3,R3)=0,"",INDEX({"Findability","Catalog","Buy","Trust","Content"},MATCH(MIN(J3,L3,N3,P3,R3),CHOOSE({1,2,3,4,5},J3,L3,N3,P3,R3),0))) -> Trust | AB3: Custom platform behind CloudFront; PDP content only visible via rendered fetch. HQ per /terms (4445 N Atlantic Blvd, Auburn Hills); privacy policy lists the Warren address.
A4: =IF(W4="","",RANK(W4,$W$2:$W$25,0)) -> 4 | B4: =IF(W4="","",1+COUNTIFS($D$2:$D$25,"Benchmark",$W$2:$W$25,">"&W4)) -> 3 | C4: Cherry Republic | D4: Benchmark | E4: Food & drink maker | F4: Shopify | G4: Glen Arbor, MI | H4: https://www.cherryrepublic.com | I4: 2026-09-28 | J4: =IFERROR(SUMIFS(Checks!$F$2:$F$1297,Checks!$A$2:$A$1297,$C4,Checks!$C$2:$C$1297,"F")/(2*COUNTIFS(Checks!$A$2:$A$1297,$C4,Checks!$C$2:$C$1297,"F",Checks!$F$2:$F$1297,">=0")),"") -> 1 | K4: =COUNTIFS(Checks!$A$2:$A$1297,$C4,Checks!$C$2:$C$1297,"F",Checks!$F$2:$F$1297,">=0") -> 7 | L4: =IFERROR(SUMIFS(Checks!$F$2:$F$1297,Checks!$A$2:$A$1297,$C4,Checks!$C$2:$C$1297,"C")/(2*COUNTIFS(Checks!$A$2:$A$1297,$C4,Checks!$C$2:$C$1297,"C",Checks!$F$2:$F$1297,">=0")),"") -> 0.75 | M4: =COUNTIFS(Checks!$A$2:$A$1297,$C4,Checks!$C$2:$C$1297,"C",Checks!$F$2:$F$1297,">=0") -> 8 | N4: =IFERROR(SUMIFS(Checks!$F$2:$F$1297,Checks!$A$2:$A$1297,$C4,Checks!$C$2:$C$1297,"B")/(2*COUNTIFS(Checks!$A$2:$A$1297,$C4,Checks!$C$2:$C$1297,"B",Checks!$F$2:$F$1297,">=0")),"") -> 1 | O4: =COUNTIFS(Checks!$A$2:$A$1297,$C4,Checks!$C$2:$C$1297,"B",Checks!$F$2:$F$1297,">=0") -> 4 | P4: =IFERROR(SUMIFS(Checks!$F$2:$F$1297,Checks!$A$2:$A$1297,$C4,Checks!$C$2:$C$1297,"T")/(2*COUNTIFS(Checks!$A$2:$A$1297,$C4,Checks!$C$2:$C$1297,"T",Checks!$F$2:$F$1297,">=0")),"") -> 1 | Q4: =COUNTIFS(Checks!$A$2:$A$1297,$C4,Checks!$C$2:$C$1297,"T",Checks!$F$2:$F$1297,">=0") -> 5 | R4: =IFERROR(SUMIFS(Checks!$F$2:$F$1297,Checks!$A$2:$A$1297,$C4,Checks!$C$2:$C$1297,"N")/(2*COUNTIFS(Checks!$A$2:$A$1297,$C4,Checks!$C$2:$C$1297,"N",Checks!$F$2:$F$1297,">=0")),"") -> 0.83333333 | S4: =COUNTIFS(Checks!$A$2:$A$1297,$C4,Checks!$C$2:$C$1297,"N",Checks!$F$2:$F$1297,">=0") -> 3 | T4: =K4+M4+O4+Q4+S4 -> 27 | U4: =T4/29 -> 0.93103448 | V4: =IF(T4>=26,"High",IF(T4>=20,"Medium","Low")) -> High | W4: =IF((IF(K4>0,Rubric!$C$3,0)+IF(M4>0,Rubric!$C$4,0)+IF(O4>0,Rubric!$C$5,0)+IF(Q4>0,Rubric!$C$6,0)+IF(S4>0,Rubric!$C$7,0))=0,"",ROUND(100*(IF(K4>0,Rubric!$C$3*J4,0)+IF(M4>0,Rubric!$C$4*L4,0)+IF(O4>0,Rubric!$C$5*N4,0)+IF(Q4>0,Rubric!$C$6*P4,0)+IF(S4>0,Rubric!$C$7*R4,0))/(IF(K4>0,Rubric!$C$3,0)+IF(M4>0,Rubric!$C$4,0)+IF(O4>0,Rubric!$C$5,0)+IF(Q4>0,Rubric!$C$6,0)+IF(S4>0,Rubric!$C$7,0)),1)) -> 90.8 | X4: =IF(W4="","",IF(W4>=Rubric!$C$11,"A",IF(W4>=Rubric!$C$12,"B",IF(W4>=Rubric!$C$13,"C",IF(W4>=Rubric!$C$14,"D","F"))))) -> A | Y4: =IF(X4="","",IF(X4="A","Benchmark",IF(X4="B","Strong",IF(X4="C","Developing",IF(X4="D","Needs work","At risk"))))) -> Benchmark | Z4: =IF(COUNT(J4,L4,N4,P4,R4)=0,"",INDEX({"Findability","Catalog","Buy","Trust","Content"},MATCH(MIN(J4,L4,N4,P4,R4),CHOOSE({1,2,3,4,5},J4,L4,N4,P4,R4),0))) -> Catalog | AB4: Shopify. Also: add store hours to the Locations page, stock state to PDPs; blog listing hides dates (only visible on the post page).
A5: =IF(W5="","",RANK(W5,$W$2:$W$25,0)) -> 5 | B5: =IF(W5="","",1+COUNTIFS($D$2:$D$25,"Benchmark",$W$2:$W$25,">"&W5)) -> 4 | C5: American Spoon | D5: Benchmark | E5: Food & drink maker | F5: Shopify | G5: Petoskey, MI | H5: https://www.spoon.com | I5: 2026-09-28 | J5: =IFERROR(SUMIFS(Checks!$F$2:$F$1297,Checks!$A$2:$A$1297,$C5,Checks!$C$2:$C$1297,"F")/(2*COUNTIFS(Checks!$A$2:$A$1297,$C5,Checks!$C$2:$C$1297,"F",Checks!$F$2:$F$1297,">=0")),"") -> 0.9 | K5: =COUNTIFS(Checks!$A$2:$A$1297,$C5,Checks!$C$2:$C$1297,"F",Checks!$F$2:$F$1297,">=0") -> 5 | L5: =IFERROR(SUMIFS(Checks!$F$2:$F$1297,Checks!$A$2:$A$1297,$C5,Checks!$C$2:$C$1297,"C")/(2*COUNTIFS(Checks!$A$2:$A$1297,$C5,Checks!$C$2:$C$1297,"C",Checks!$F$2:$F$1297,">=0")),"") -> 0.875 | M5: =COUNTIFS(Checks!$A$2:$A$1297,$C5,Checks!$C$2:$C$1297,"C",Checks!$F$2:$F$1297,">=0") -> 8 | N5: =IFERROR(SUMIFS(Checks!$F$2:$F$1297,Checks!$A$2:$A$1297,$C5,Checks!$C$2:$C$1297,"B")/(2*COUNTIFS(Checks!$A$2:$A$1297,$C5,Checks!$C$2:$C$1297,"B",Checks!$F$2:$F$1297,">=0")),"") -> 0.875 | O5: =COUNTIFS(Checks!$A$2:$A$1297,$C5,Checks!$C$2:$C$1297,"B",Checks!$F$2:$F$1297,">=0") -> 4 | P5: =IFERROR(SUMIFS(Checks!$F$2:$F$1297,Checks!$A$2:$A$1297,$C5,Checks!$C$2:$C$1297,"T")/(2*COUNTIFS(Checks!$A$2:$A$1297,$C5,Checks!$C$2:$C$1297,"T",Checks!$F$2:$F$1297,">=0")),"") -> 1 | Q5: =COUNTIFS(Checks!$A$2:$A$1297,$C5,Checks!$C$2:$C$1297,"T",Checks!$F$2:$F$1297,">=0") -> 5 | R5: =IFERROR(SUMIFS(Checks!$F$2:$F$1297,Checks!$A$2:$A$1297,$C5,Checks!$C$2:$C$1297,"N")/(2*COUNTIFS(Checks!$A$2:$A$1297,$C5,Checks!$C$2:$C$1297,"N",Checks!$F$2:$F$1297,">=0")),"") -> 0.83333333 | S5: =COUNTIFS(Checks!$A$2:$A$1297,$C5,Checks!$C$2:$C$1297,"N",Checks!$F$2:$F$1297,">=0") -> 3 | T5: =K5+M5+O5+Q5+S5 -> 25 | U5: =T5/29 -> 0.86206897 | V5: =IF(T5>=26,"High",IF(T5>=20,"Medium","Low")) -> Medium | W5: =IF((IF(K5>0,Rubric!$C$3,0)+IF(M5>0,Rubric!$C$4,0)+IF(O5>0,Rubric!$C$5,0)+IF(Q5>0,Rubric!$C$6,0)+IF(S5>0,Rubric!$C$7,0))=0,"",ROUND(100*(IF(K5>0,Rubric!$C$3*J5,0)+IF(M5>0,Rubric!$C$4*L5,0)+IF(O5>0,Rubric!$C$5*N5,0)+IF(Q5>0,Rubric!$C$6*P5,0)+IF(S5>0,Rubric!$C$7*R5,0))/(IF(K5>0,Rubric!$C$3,0)+IF(M5>0,Rubric!$C$4,0)+IF(O5>0,Rubric!$C$5,0)+IF(Q5>0,Rubric!$C$6,0)+IF(S5>0,Rubric!$C$7,0)),1)) -> 89.6 | X5: =IF(W5="","",IF(W5>=Rubric!$C$11,"A",IF(W5>=Rubric!$C$12,"B",IF(W5>=Rubric!$C$13,"C",IF(W5>=Rubric!$C$14,"D","F"))))) -> A | Y5: =IF(X5="","",IF(X5="A","Benchmark",IF(X5="B","Strong",IF(X5="C","Developing",IF(X5="D","Needs work","At risk"))))) -> Benchmark | Z5: =IF(COUNT(J5,L5,N5,P5,R5)=0,"",INDEX({"Findability","Catalog","Buy","Trust","Content"},MATCH(MIN(J5,L5,N5,P5,R5),CHOOSE({1,2,3,4,5},J5,L5,N5,P5,R5),0))) -> Content | AB5: Shopify. WebFetch surfaced no <head> meta block for spoon.com, so meta description and canonical are U. Collection handles carry a 'website-' prefix; /blogs/recipes 404s (recipes live under /pages/).
A6: =IF(W6="","",RANK(W6,$W$2:$W$25,0)) -> 6 | B6: =IF(W6="","",1+COUNTIFS($D$2:$D$25,"Benchmark",$W$2:$W$25,">"&W6)) -> 5 | C6: Bissell | D6: Benchmark | E6: Brand & maker | F6: Salesforce Commerce | G6: Grand Rapids, MI | H6: https://www.bissell.com | I6: 2026-09-28 | J6: =IFERROR(SUMIFS(Checks!$F$2:$F$1297,Checks!$A$2:$A$1297,$C6,Checks!$C$2:$C$1297,"F")/(2*COUNTIFS(Checks!$A$2:$A$1297,$C6,Checks!$C$2:$C$1297,"F",Checks!$F$2:$F$1297,">=0")),"") -> 1 | K6: =COUNTIFS(Checks!$A$2:$A$1297,$C6,Checks!$C$2:$C$1297,"F",Checks!$F$2:$F$1297,">=0") -> 7 | L6: =IFERROR(SUMIFS(Checks!$F$2:$F$1297,Checks!$A$2:$A$1297,$C6,Checks!$C$2:$C$1297,"C")/(2*COUNTIFS(Checks!$A$2:$A$1297,$C6,Checks!$C$2:$C$1297,"C",Checks!$F$2:$F$1297,">=0")),"") -> 0.8125 | M6: =COUNTIFS(Checks!$A$2:$A$1297,$C6,Checks!$C$2:$C$1297,"C",Checks!$F$2:$F$1297,">=0") -> 8 | N6: =IFERROR(SUMIFS(Checks!$F$2:$F$1297,Checks!$A$2:$A$1297,$C6,Checks!$C$2:$C$1297,"B")/(2*COUNTIFS(Checks!$A$2:$A$1297,$C6,Checks!$C$2:$C$1297,"B",Checks!$F$2:$F$1297,">=0")),"") -> 0.83333333 | O6: =COUNTIFS(Checks!$A$2:$A$1297,$C6,Checks!$C$2:$C$1297,"B",Checks!$F$2:$F$1297,">=0") -> 3 | P6: =IFERROR(SUMIFS(Checks!$F$2:$F$1297,Checks!$A$2:$A$1297,$C6,Checks!$C$2:$C$1297,"T")/(2*COUNTIFS(Checks!$A$2:$A$1297,$C6,Checks!$C$2:$C$1297,"T",Checks!$F$2:$F$1297,">=0")),"") -> 1 | Q6: =COUNTIFS(Checks!$A$2:$A$1297,$C6,Checks!$C$2:$C$1297,"T",Checks!$F$2:$F$1297,">=0") -> 4 | R6: =IFERROR(SUMIFS(Checks!$F$2:$F$1297,Checks!$A$2:$A$1297,$C6,Checks!$C$2:$C$1297,"N")/(2*COUNTIFS(Checks!$A$2:$A$1297,$C6,Checks!$C$2:$C$1297,"N",Checks!$F$2:$F$1297,">=0")),"") -> 0.75 | S6: =COUNTIFS(Checks!$A$2:$A$1297,$C6,Checks!$C$2:$C$1297,"N",Checks!$F$2:$F$1297,">=0") -> 2 | T6: =K6+M6+O6+Q6+S6 -> 24 | U6: =T6/29 -> 0.82758621 | V6: =IF(T6>=26,"High",IF(T6>=20,"Medium","Low")) -> Medium | W6: =IF((IF(K6>0,Rubric!$C$3,0)+IF(M6>0,Rubric!$C$4,0)+IF(O6>0,Rubric!$C$5,0)+IF(Q6>0,Rubric!$C$6,0)+IF(S6>0,Rubric!$C$7,0))=0,"",ROUND(100*(IF(K6>0,Rubric!$C$3*J6,0)+IF(M6>0,Rubric!$C$4*L6,0)+IF(O6>0,Rubric!$C$5*N6,0)+IF(Q6>0,Rubric!$C$6*P6,0)+IF(S6>0,Rubric!$C$7*R6,0))/(IF(K6>0,Rubric!$C$3,0)+IF(M6>0,Rubric!$C$4,0)+IF(O6>0,Rubric!$C$5,0)+IF(Q6>0,Rubric!$C$6,0)+IF(S6>0,Rubric!$C$7,0)),1)) -> 88.5 | X6: =IF(W6="","",IF(W6>=Rubric!$C$11,"A",IF(W6>=Rubric!$C$12,"B",IF(W6>=Rubric!$C$13,"C",IF(W6>=Rubric!$C$14,"D","F"))))) -> A | Y6: =IF(X6="","",IF(X6="A","Benchmark",IF(X6="B","Strong",IF(X6="C","Developing",IF(X6="D","Needs work","At risk"))))) -> Benchmark | Z6: =IF(COUNT(J6,L6,N6,P6,R6)=0,"",INDEX({"Findability","Catalog","Buy","Trust","Content"},MATCH(MIN(J6,L6,N6,P6,R6),CHOOSE({1,2,3,4,5},J6,L6,N6,P6,R6),0))) -> Content | AB6: HQ confirmed via Terms/Privacy: BISSELL Homecare, Inc., 2345 Walker Avenue NW, Grand Rapids, MI 49544. support.bissell.com is robots-disallowed for fetchers. robots.txt blocks ClaudeBot, GPTBot, Google-Extended, Applebot-Extended, Meta-ExternalAgent. Social icons not present in fetched footer text.
A7: =IF(W7="","",RANK(W7,$W$2:$W$25,0)) -> 7 | B7: =IF(W7="","",1+COUNTIFS($D$2:$D$25,"Benchmark",$W$2:$W$25,">"&W7)) -> 6 | C7: La-Z-Boy | D7: Benchmark | E7: Brand & maker | F7: Custom | G7: Monroe, MI | H7: https://www.la-z-boy.com | I7: 2026-09-28 | J7: =IFERROR(SUMIFS(Checks!$F$2:$F$1297,Checks!$A$2:$A$1297,$C7,Checks!$C$2:$C$1297,"F")/(2*COUNTIFS(Checks!$A$2:$A$1297,$C7,Checks!$C$2:$C$1297,"F",Checks!$F$2:$F$1297,">=0")),"") -> 0.85714286 | K7: =COUNTIFS(Checks!$A$2:$A$1297,$C7,Checks!$C$2:$C$1297,"F",Checks!$F$2:$F$1297,">=0") -> 7 | L7: =IFERROR(SUMIFS(Checks!$F$2:$F$1297,Checks!$A$2:$A$1297,$C7,Checks!$C$2:$C$1297,"C")/(2*COUNTIFS(Checks!$A$2:$A$1297,$C7,Checks!$C$2:$C$1297,"C",Checks!$F$2:$F$1297,">=0")),"") -> 0.9375 | M7: =COUNTIFS(Checks!$A$2:$A$1297,$C7,Checks!$C$2:$C$1297,"C",Checks!$F$2:$F$1297,">=0") -> 8 | N7: =IFERROR(SUMIFS(Checks!$F$2:$F$1297,Checks!$A$2:$A$1297,$C7,Checks!$C$2:$C$1297,"B")/(2*COUNTIFS(Checks!$A$2:$A$1297,$C7,Checks!$C$2:$C$1297,"B",Checks!$F$2:$F$1297,">=0")),"") -> 0.875 | O7: =COUNTIFS(Checks!$A$2:$A$1297,$C7,Checks!$C$2:$C$1297,"B",Checks!$F$2:$F$1297,">=0") -> 4 | P7: =IFERROR(SUMIFS(Checks!$F$2:$F$1297,Checks!$A$2:$A$1297,$C7,Checks!$C$2:$C$1297,"T")/(2*COUNTIFS(Checks!$A$2:$A$1297,$C7,Checks!$C$2:$C$1297,"T",Checks!$F$2:$F$1297,">=0")),"") -> 0.9 | Q7: =COUNTIFS(Checks!$A$2:$A$1297,$C7,Checks!$C$2:$C$1297,"T",Checks!$F$2:$F$1297,">=0") -> 5 | R7: =IFERROR(SUMIFS(Checks!$F$2:$F$1297,Checks!$A$2:$A$1297,$C7,Checks!$C$2:$C$1297,"N")/(2*COUNTIFS(Checks!$A$2:$A$1297,$C7,Checks!$C$2:$C$1297,"N",Checks!$F$2:$F$1297,">=0")),"") -> 0.66666667 | S7: =COUNTIFS(Checks!$A$2:$A$1297,$C7,Checks!$C$2:$C$1297,"N",Checks!$F$2:$F$1297,">=0") -> 3 | T7: =K7+M7+O7+Q7+S7 -> 27 | U7: =T7/29 -> 0.93103448 | V7: =IF(T7>=26,"High",IF(T7>=20,"Medium","Low")) -> High | W7: =IF((IF(K7>0,Rubric!$C$3,0)+IF(M7>0,Rubric!$C$4,0)+IF(O7>0,Rubric!$C$5,0)+IF(Q7>0,Rubric!$C$6,0)+IF(S7>0,Rubric!$C$7,0))=0,"",ROUND(100*(IF(K7>0,Rubric!$C$3*J7,0)+IF(M7>0,Rubric!$C$4*L7,0)+IF(O7>0,Rubric!$C$5*N7,0)+IF(Q7>0,Rubric!$C$6*P7,0)+IF(S7>0,Rubric!$C$7*R7,0))/(IF(K7>0,Rubric!$C$3,0)+IF(M7>0,Rubric!$C$4,0)+IF(O7>0,Rubric!$C$5,0)+IF(Q7>0,Rubric!$C$6,0)+IF(S7>0,Rubric!$C$7,0)),1)) -> 87.2 | X7: =IF(W7="","",IF(W7>=Rubric!$C$11,"A",IF(W7>=Rubric!$C$12,"B",IF(W7>=Rubric!$C$13,"C",IF(W7>=Rubric!$C$14,"D","F"))))) -> A | Y7: =IF(X7="","",IF(X7="A","Benchmark",IF(X7="B","Strong",IF(X7="C","Developing",IF(X7="D","Needs work","At risk"))))) -> Benchmark | Z7: =IF(COUNT(J7,L7,N7,P7,R7)=0,"",INDEX({"Findability","Catalog","Buy","Trust","Content"},MATCH(MIN(J7,L7,N7,P7,R7),CHOOSE({1,2,3,4,5},J7,L7,N7,P7,R7),0))) -> Content | AB7: HQ confirmed as One La-Z-Boy Drive, Monroe, MI 48162 (Privacy Notice); homepage/contact default to the Columbus, OH gallery store. Exa fallback hit an Akamai 'Client Challenge'; WebFetch worked. Return policy is strict (3-day window, up to 30% restocking) and is not linked from the PDP itself.
A8: =IF(W8="","",RANK(W8,$W$2:$W$25,0)) -> 8 | B8: =IF(W8="","",1+COUNTIFS($D$2:$D$25,"Benchmark",$W$2:$W$25,">"&W8)) -> 7 | C8: Shinola | D8: Benchmark | E8: Brand & maker | F8: Shopify | G8: Detroit, MI | H8: https://www.shinola.com | I8: 2026-09-28 | J8: =IFERROR(SUMIFS(Checks!$F$2:$F$1297,Checks!$A$2:$A$1297,$C8,Checks!$C$2:$C$1297,"F")/(2*COUNTIFS(Checks!$A$2:$A$1297,$C8,Checks!$C$2:$C$1297,"F",Checks!$F$2:$F$1297,">=0")),"") -> 0.92857143 | K8: =COUNTIFS(Checks!$A$2:$A$1297,$C8,Checks!$C$2:$C$1297,"F",Checks!$F$2:$F$1297,">=0") -> 7 | L8: =IFERROR(SUMIFS(Checks!$F$2:$F$1297,Checks!$A$2:$A$1297,$C8,Checks!$C$2:$C$1297,"C")/(2*COUNTIFS(Checks!$A$2:$A$1297,$C8,Checks!$C$2:$C$1297,"C",Checks!$F$2:$F$1297,">=0")),"") -> 0.8125 | M8: =COUNTIFS(Checks!$A$2:$A$1297,$C8,Checks!$C$2:$C$1297,"C",Checks!$F$2:$F$1297,">=0") -> 8 | N8: =IFERROR(SUMIFS(Checks!$F$2:$F$1297,Checks!$A$2:$A$1297,$C8,Checks!$C$2:$C$1297,"B")/(2*COUNTIFS(Checks!$A$2:$A$1297,$C8,Checks!$C$2:$C$1297,"B",Checks!$F$2:$F$1297,">=0")),"") -> 0.875 | O8: =COUNTIFS(Checks!$A$2:$A$1297,$C8,Checks!$C$2:$C$1297,"B",Checks!$F$2:$F$1297,">=0") -> 4 | P8: =IFERROR(SUMIFS(Checks!$F$2:$F$1297,Checks!$A$2:$A$1297,$C8,Checks!$C$2:$C$1297,"T")/(2*COUNTIFS(Checks!$A$2:$A$1297,$C8,Checks!$C$2:$C$1297,"T",Checks!$F$2:$F$1297,">=0")),"") -> 1 | Q8: =COUNTIFS(Checks!$A$2:$A$1297,$C8,Checks!$C$2:$C$1297,"T",Checks!$F$2:$F$1297,">=0") -> 4 | R8: =IFERROR(SUMIFS(Checks!$F$2:$F$1297,Checks!$A$2:$A$1297,$C8,Checks!$C$2:$C$1297,"N")/(2*COUNTIFS(Checks!$A$2:$A$1297,$C8,Checks!$C$2:$C$1297,"N",Checks!$F$2:$F$1297,">=0")),"") -> 0.66666667 | S8: =COUNTIFS(Checks!$A$2:$A$1297,$C8,Checks!$C$2:$C$1297,"N",Checks!$F$2:$F$1297,">=0") -> 3 | T8: =K8+M8+O8+Q8+S8 -> 26 | U8: =T8/29 -> 0.89655172 | V8: =IF(T8>=26,"High",IF(T8>=20,"Medium","Low")) -> High | W8: =IF((IF(K8>0,Rubric!$C$3,0)+IF(M8>0,Rubric!$C$4,0)+IF(O8>0,Rubric!$C$5,0)+IF(Q8>0,Rubric!$C$6,0)+IF(S8>0,Rubric!$C$7,0))=0,"",ROUND(100*(IF(K8>0,Rubric!$C$3*J8,0)+IF(M8>0,Rubric!$C$4*L8,0)+IF(O8>0,Rubric!$C$5*N8,0)+IF(Q8>0,Rubric!$C$6*P8,0)+IF(S8>0,Rubric!$C$7*R8,0))/(IF(K8>0,Rubric!$C$3,0)+IF(M8>0,Rubric!$C$4,0)+IF(O8>0,Rubric!$C$5,0)+IF(Q8>0,Rubric!$C$6,0)+IF(S8>0,Rubric!$C$7,0)),1)) -> 86.8 | X8: =IF(W8="","",IF(W8>=Rubric!$C$11,"A",IF(W8>=Rubric!$C$12,"B",IF(W8>=Rubric!$C$13,"C",IF(W8>=Rubric!$C$14,"D","F"))))) -> A | Y8: =IF(X8="","",IF(X8="A","Benchmark",IF(X8="B","Strong",IF(X8="C","Developing",IF(X8="D","Needs work","At risk"))))) -> Benchmark | Z8: =IF(COUNT(J8,L8,N8,P8,R8)=0,"",INDEX({"Findability","Catalog","Buy","Trust","Content"},MATCH(MIN(J8,L8,N8,P8,R8),CHOOSE({1,2,3,4,5},J8,L8,N8,P8,R8),0))) -> Content | AB8: Collection/search product grids and Stockist store locator render client-side; fetchers saw 'No products found' although subcollections report counts (Men's Watches 134). HQ address 485 W. Milwaukee Ave, Detroit from Terms of Use. /pages/shinola-guarantee shows a theme 'This page is protected' notice. Social links not present in fetched footer text (icon links may be stripped).
A9: =IF(W9="","",RANK(W9,$W$2:$W$25,0)) -> 9 | B9: =IF(W9="","",1+COUNTIFS($D$2:$D$25,"Benchmark",$W$2:$W$25,">"&W9)) -> 8 | C9: Zingerman's Mail Order | D9: Benchmark | E9: Food & drink maker | F9: Custom | G9: Ann Arbor, MI | H9: https://www.zingermans.com | I9: 2026-09-28 | J9: =IFERROR(SUMIFS(Checks!$F$2:$F$1297,Checks!$A$2:$A$1297,$C9,Checks!$C$2:$C$1297,"F")/(2*COUNTIFS(Checks!$A$2:$A$1297,$C9,Checks!$C$2:$C$1297,"F",Checks!$F$2:$F$1297,">=0")),"") -> 0.85714286 | K9: =COUNTIFS(Checks!$A$2:$A$1297,$C9,Checks!$C$2:$C$1297,"F",Checks!$F$2:$F$1297,">=0") -> 7 | L9: =IFERROR(SUMIFS(Checks!$F$2:$F$1297,Checks!$A$2:$A$1297,$C9,Checks!$C$2:$C$1297,"C")/(2*COUNTIFS(Checks!$A$2:$A$1297,$C9,Checks!$C$2:$C$1297,"C",Checks!$F$2:$F$1297,">=0")),"") -> 0.85714286 | M9: =COUNTIFS(Checks!$A$2:$A$1297,$C9,Checks!$C$2:$C$1297,"C",Checks!$F$2:$F$1297,">=0") -> 7 | N9: =IFERROR(SUMIFS(Checks!$F$2:$F$1297,Checks!$A$2:$A$1297,$C9,Checks!$C$2:$C$1297,"B")/(2*COUNTIFS(Checks!$A$2:$A$1297,$C9,Checks!$C$2:$C$1297,"B",Checks!$F$2:$F$1297,">=0")),"") -> 0.9 | O9: =COUNTIFS(Checks!$A$2:$A$1297,$C9,Checks!$C$2:$C$1297,"B",Checks!$F$2:$F$1297,">=0") -> 5 | P9: =IFERROR(SUMIFS(Checks!$F$2:$F$1297,Checks!$A$2:$A$1297,$C9,Checks!$C$2:$C$1297,"T")/(2*COUNTIFS(Checks!$A$2:$A$1297,$C9,Checks!$C$2:$C$1297,"T",Checks!$F$2:$F$1297,">=0")),"") -> 0.9 | Q9: =COUNTIFS(Checks!$A$2:$A$1297,$C9,Checks!$C$2:$C$1297,"T",Checks!$F$2:$F$1297,">=0") -> 5 | R9: =IFERROR(SUMIFS(Checks!$F$2:$F$1297,Checks!$A$2:$A$1297,$C9,Checks!$C$2:$C$1297,"N")/(2*COUNTIFS(Checks!$A$2:$A$1297,$C9,Checks!$C$2:$C$1297,"N",Checks!$F$2:$F$1297,">=0")),"") -> 0.66666667 | S9: =COUNTIFS(Checks!$A$2:$A$1297,$C9,Checks!$C$2:$C$1297,"N",Checks!$F$2:$F$1297,">=0") -> 3 | T9: =K9+M9+O9+Q9+S9 -> 27 | U9: =T9/29 -> 0.93103448 | V9: =IF(T9>=26,"High",IF(T9>=20,"Medium","Low")) -> High | W9: =IF((IF(K9>0,Rubric!$C$3,0)+IF(M9>0,Rubric!$C$4,0)+IF(O9>0,Rubric!$C$5,0)+IF(Q9>0,Rubric!$C$6,0)+IF(S9>0,Rubric!$C$7,0))=0,"",ROUND(100*(IF(K9>0,Rubric!$C$3*J9,0)+IF(M9>0,Rubric!$C$4*L9,0)+IF(O9>0,Rubric!$C$5*N9,0)+IF(Q9>0,Rubric!$C$6*P9,0)+IF(S9>0,Rubric!$C$7*R9,0))/(IF(K9>0,Rubric!$C$3,0)+IF(M9>0,Rubric!$C$4,0)+IF(O9>0,Rubric!$C$5,0)+IF(Q9>0,Rubric!$C$6,0)+IF(S9>0,Rubric!$C$7,0)),1)) -> 85.3 | X9: =IF(W9="","",IF(W9>=Rubric!$C$11,"A",IF(W9>=Rubric!$C$12,"B",IF(W9>=Rubric!$C$13,"C",IF(W9>=Rubric!$C$14,"D","F"))))) -> A | Y9: =IF(X9="","",IF(X9="A","Benchmark",IF(X9="B","Strong",IF(X9="C","Developing",IF(X9="D","Needs work","At risk"))))) -> Benchmark | Z9: =IF(COUNT(J9,L9,N9,P9,R9)=0,"",INDEX({"Findability","Catalog","Buy","Trust","Content"},MATCH(MIN(J9,L9,N9,P9,R9),CHOOSE({1,2,3,4,5},J9,L9,N9,P9,R9),0))) -> Content | AB9: Custom ASP.NET platform (Category.aspx, sitemap.aspx). Category URLs are query strings. No Terms page found; privacy policy lives on zingermanscommunity.com.
A10: =IF(W10="","",RANK(W10,$W$2:$W$25,0)) -> 10 | B10: =IF(W10="","",1+COUNTIFS($D$2:$D$25,"Benchmark",$W$2:$W$25,">"&W10)) -> 9 | C10: Dunham's Sports | D10: Benchmark | E10: Retail chain | F10: Custom | G10: Troy, MI | H10: https://www.dunhamssports.com | I10: 2026-09-28 | J10: =IFERROR(SUMIFS(Checks!$F$2:$F$1297,Checks!$A$2:$A$1297,$C10,Checks!$C$2:$C$1297,"F")/(2*COUNTIFS(Checks!$A$2:$A$1297,$C10,Checks!$C$2:$C$1297,"F",Checks!$F$2:$F$1297,">=0")),"") -> 0.85714286 | K10: =COUNTIFS(Checks!$A$2:$A$1297,$C10,Checks!$C$2:$C$1297,"F",Checks!$F$2:$F$1297,">=0") -> 7 | L10: =IFERROR(SUMIFS(Checks!$F$2:$F$1297,Checks!$A$2:$A$1297,$C10,Checks!$C$2:$C$1297,"C")/(2*COUNTIFS(Checks!$A$2:$A$1297,$C10,Checks!$C$2:$C$1297,"C",Checks!$F$2:$F$1297,">=0")),"") -> 0.78571429 | M10: =COUNTIFS(Checks!$A$2:$A$1297,$C10,Checks!$C$2:$C$1297,"C",Checks!$F$2:$F$1297,">=0") -> 7 | N10: =IFERROR(SUMIFS(Checks!$F$2:$F$1297,Checks!$A$2:$A$1297,$C10,Checks!$C$2:$C$1297,"B")/(2*COUNTIFS(Checks!$A$2:$A$1297,$C10,Checks!$C$2:$C$1297,"B",Checks!$F$2:$F$1297,">=0")),"") -> 0.75 | O10: =COUNTIFS(Checks!$A$2:$A$1297,$C10,Checks!$C$2:$C$1297,"B",Checks!$F$2:$F$1297,">=0") -> 4 | P10: =IFERROR(SUMIFS(Checks!$F$2:$F$1297,Checks!$A$2:$A$1297,$C10,Checks!$C$2:$C$1297,"T")/(2*COUNTIFS(Checks!$A$2:$A$1297,$C10,Checks!$C$2:$C$1297,"T",Checks!$F$2:$F$1297,">=0")),"") -> 1 | Q10: =COUNTIFS(Checks!$A$2:$A$1297,$C10,Checks!$C$2:$C$1297,"T",Checks!$F$2:$F$1297,">=0") -> 4 | R10: =IFERROR(SUMIFS(Checks!$F$2:$F$1297,Checks!$A$2:$A$1297,$C10,Checks!$C$2:$C$1297,"N")/(2*COUNTIFS(Checks!$A$2:$A$1297,$C10,Checks!$C$2:$C$1297,"N",Checks!$F$2:$F$1297,">=0")),"") -> 0.66666667 | S10: =COUNTIFS(Checks!$A$2:$A$1297,$C10,Checks!$C$2:$C$1297,"N",Checks!$F$2:$F$1297,">=0") -> 3 | T10: =K10+M10+O10+Q10+S10 -> 25 | U10: =T10/29 -> 0.86206897 | V10: =IF(T10>=26,"High",IF(T10>=20,"Medium","Low")) -> Medium | W10: =IF((IF(K10>0,Rubric!$C$3,0)+IF(M10>0,Rubric!$C$4,0)+IF(O10>0,Rubric!$C$5,0)+IF(Q10>0,Rubric!$C$6,0)+IF(S10>0,Rubric!$C$7,0))=0,"",ROUND(100*(IF(K10>0,Rubric!$C$3*J10,0)+IF(M10>0,Rubric!$C$4*L10,0)+IF(O10>0,Rubric!$C$5*N10,0)+IF(Q10>0,Rubric!$C$6*P10,0)+IF(S10>0,Rubric!$C$7*R10,0))/(IF(K10>0,Rubric!$C$3,0)+IF(M10>0,Rubric!$C$4,0)+IF(O10>0,Rubric!$C$5,0)+IF(Q10>0,Rubric!$C$6,0)+IF(S10>0,Rubric!$C$7,0)),1)) -> 81.7 | X10: =IF(W10="","",IF(W10>=Rubric!$C$11,"A",IF(W10>=Rubric!$C$12,"B",IF(W10>=Rubric!$C$13,"C",IF(W10>=Rubric!$C$14,"D","F"))))) -> B | Y10: =IF(X10="","",IF(X10="A","Benchmark",IF(X10="B","Strong",IF(X10="C","Developing",IF(X10="D","Needs work","At risk"))))) -> Strong | Z10: =IF(COUNT(J10,L10,N10,P10,R10)=0,"",INDEX({"Findability","Catalog","Buy","Trust","Content"},MATCH(MIN(J10,L10,N10,P10,R10),CHOOSE({1,2,3,4,5},J10,L10,N10,P10,R10),0))) -> Content | AB10: Shopware 6 storefront; the mega-menu crowds page content out of text fetches, so search box, add-to-cart label and social links could not be confirmed.
A11: =IF(W11="","",RANK(W11,$W$2:$W$25,0)) -> 11 | B11: =IF(W11="","",1+COUNTIFS($D$2:$D$25,"Benchmark",$W$2:$W$25,">"&W11)) -> 10 | C11: Apparel Wholesale Depot | D11: Benchmark | E11: Wholesale / B2B | F11: Shopify | G11: Warren, MI | H11: https://www.apparelwholesaledepot.com | I11: 2026-09-28 | J11: =IFERROR(SUMIFS(Checks!$F$2:$F$1297,Checks!$A$2:$A$1297,$C11,Checks!$C$2:$C$1297,"F")/(2*COUNTIFS(Checks!$A$2:$A$1297,$C11,Checks!$C$2:$C$1297,"F",Checks!$F$2:$F$1297,">=0")),"") -> 0.78571429 | K11: =COUNTIFS(Checks!$A$2:$A$1297,$C11,Checks!$C$2:$C$1297,"F",Checks!$F$2:$F$1297,">=0") -> 7 | L11: =IFERROR(SUMIFS(Checks!$F$2:$F$1297,Checks!$A$2:$A$1297,$C11,Checks!$C$2:$C$1297,"C")/(2*COUNTIFS(Checks!$A$2:$A$1297,$C11,Checks!$C$2:$C$1297,"C",Checks!$F$2:$F$1297,">=0")),"") -> 0.9375 | M11: =COUNTIFS(Checks!$A$2:$A$1297,$C11,Checks!$C$2:$C$1297,"C",Checks!$F$2:$F$1297,">=0") -> 8 | N11: =IFERROR(SUMIFS(Checks!$F$2:$F$1297,Checks!$A$2:$A$1297,$C11,Checks!$C$2:$C$1297,"B")/(2*COUNTIFS(Checks!$A$2:$A$1297,$C11,Checks!$C$2:$C$1297,"B",Checks!$F$2:$F$1297,">=0")),"") -> 0.6 | O11: =COUNTIFS(Checks!$A$2:$A$1297,$C11,Checks!$C$2:$C$1297,"B",Checks!$F$2:$F$1297,">=0") -> 5 | P11: =IFERROR(SUMIFS(Checks!$F$2:$F$1297,Checks!$A$2:$A$1297,$C11,Checks!$C$2:$C$1297,"T")/(2*COUNTIFS(Checks!$A$2:$A$1297,$C11,Checks!$C$2:$C$1297,"T",Checks!$F$2:$F$1297,">=0")),"") -> 1 | Q11: =COUNTIFS(Checks!$A$2:$A$1297,$C11,Checks!$C$2:$C$1297,"T",Checks!$F$2:$F$1297,">=0") -> 5 | R11: =IFERROR(SUMIFS(Checks!$F$2:$F$1297,Checks!$A$2:$A$1297,$C11,Checks!$C$2:$C$1297,"N")/(2*COUNTIFS(Checks!$A$2:$A$1297,$C11,Checks!$C$2:$C$1297,"N",Checks!$F$2:$F$1297,">=0")),"") -> 0.66666667 | S11: =COUNTIFS(Checks!$A$2:$A$1297,$C11,Checks!$C$2:$C$1297,"N",Checks!$F$2:$F$1297,">=0") -> 3 | T11: =K11+M11+O11+Q11+S11 -> 28 | U11: =T11/29 -> 0.96551724 | V11: =IF(T11>=26,"High",IF(T11>=20,"Medium","Low")) -> High | W11: =IF((IF(K11>0,Rubric!$C$3,0)+IF(M11>0,Rubric!$C$4,0)+IF(O11>0,Rubric!$C$5,0)+IF(Q11>0,Rubric!$C$6,0)+IF(S11>0,Rubric!$C$7,0))=0,"",ROUND(100*(IF(K11>0,Rubric!$C$3*J11,0)+IF(M11>0,Rubric!$C$4*L11,0)+IF(O11>0,Rubric!$C$5*N11,0)+IF(Q11>0,Rubric!$C$6*P11,0)+IF(S11>0,Rubric!$C$7*R11,0))/(IF(K11>0,Rubric!$C$3,0)+IF(M11>0,Rubric!$C$4,0)+IF(O11>0,Rubric!$C$5,0)+IF(Q11>0,Rubric!$C$6,0)+IF(S11>0,Rubric!$C$7,0)),1)) -> 81.4 | X11: =IF(W11="","",IF(W11>=Rubric!$C$11,"A",IF(W11>=Rubric!$C$12,"B",IF(W11>=Rubric!$C$13,"C",IF(W11>=Rubric!$C$14,"D","F"))))) -> B | Y11: =IF(X11="","",IF(X11="A","Benchmark",IF(X11="B","Strong",IF(X11="C","Developing",IF(X11="D","Needs work","At risk"))))) -> Strong | Z11: =IF(COUNT(J11,L11,N11,P11,R11)=0,"",INDEX({"Findability","Catalog","Buy","Trust","Content"},MATCH(MIN(J11,L11,N11,P11,R11),CHOOSE({1,2,3,4,5},J11,L11,N11,P11,R11),0))) -> Buy | AB11: Single-location wholesaler with a retail-style Shopify checkout; wholesale pricing is phone-only. /pages/contact returns 404 (the live page is /pages/contact-us). Homepage canonical and meta description were not returned in two separate fetches while product and collection pages showed both.
A12: =IF(W12="","",RANK(W12,$W$2:$W$25,0)) -> 12 | B12: =IF(W12="","",1+COUNTIFS($D$2:$D$25,"Benchmark",$W$2:$W$25,">"&W12)) -> 11 | C12: Made In Detroit | D12: Benchmark | E12: Brand & maker | F12: Shopify | G12: Clarkston, MI | H12: https://www.madeindetroit.com | I12: 2026-09-28 | J12: =IFERROR(SUMIFS(Checks!$F$2:$F$1297,Checks!$A$2:$A$1297,$C12,Checks!$C$2:$C$1297,"F")/(2*COUNTIFS(Checks!$A$2:$A$1297,$C12,Checks!$C$2:$C$1297,"F",Checks!$F$2:$F$1297,">=0")),"") -> 1 | K12: =COUNTIFS(Checks!$A$2:$A$1297,$C12,Checks!$C$2:$C$1297,"F",Checks!$F$2:$F$1297,">=0") -> 7 | L12: =IFERROR(SUMIFS(Checks!$F$2:$F$1297,Checks!$A$2:$A$1297,$C12,Checks!$C$2:$C$1297,"C")/(2*COUNTIFS(Checks!$A$2:$A$1297,$C12,Checks!$C$2:$C$1297,"C",Checks!$F$2:$F$1297,">=0")),"") -> 0.75 | M12: =COUNTIFS(Checks!$A$2:$A$1297,$C12,Checks!$C$2:$C$1297,"C",Checks!$F$2:$F$1297,">=0") -> 8 | N12: =IFERROR(SUMIFS(Checks!$F$2:$F$1297,Checks!$A$2:$A$1297,$C12,Checks!$C$2:$C$1297,"B")/(2*COUNTIFS(Checks!$A$2:$A$1297,$C12,Checks!$C$2:$C$1297,"B",Checks!$F$2:$F$1297,">=0")),"") -> 0.75 | O12: =COUNTIFS(Checks!$A$2:$A$1297,$C12,Checks!$C$2:$C$1297,"B",Checks!$F$2:$F$1297,">=0") -> 4 | P12: =IFERROR(SUMIFS(Checks!$F$2:$F$1297,Checks!$A$2:$A$1297,$C12,Checks!$C$2:$C$1297,"T")/(2*COUNTIFS(Checks!$A$2:$A$1297,$C12,Checks!$C$2:$C$1297,"T",Checks!$F$2:$F$1297,">=0")),"") -> 1 | Q12: =COUNTIFS(Checks!$A$2:$A$1297,$C12,Checks!$C$2:$C$1297,"T",Checks!$F$2:$F$1297,">=0") -> 4 | R12: =IFERROR(SUMIFS(Checks!$F$2:$F$1297,Checks!$A$2:$A$1297,$C12,Checks!$C$2:$C$1297,"N")/(2*COUNTIFS(Checks!$A$2:$A$1297,$C12,Checks!$C$2:$C$1297,"N",Checks!$F$2:$F$1297,">=0")),"") -> 0.33333333 | S12: =COUNTIFS(Checks!$A$2:$A$1297,$C12,Checks!$C$2:$C$1297,"N",Checks!$F$2:$F$1297,">=0") -> 3 | T12: =K12+M12+O12+Q12+S12 -> 26 | U12: =T12/29 -> 0.89655172 | V12: =IF(T12>=26,"High",IF(T12>=20,"Medium","Low")) -> High | W12: =IF((IF(K12>0,Rubric!$C$3,0)+IF(M12>0,Rubric!$C$4,0)+IF(O12>0,Rubric!$C$5,0)+IF(Q12>0,Rubric!$C$6,0)+IF(S12>0,Rubric!$C$7,0))=0,"",ROUND(100*(IF(K12>0,Rubric!$C$3*J12,0)+IF(M12>0,Rubric!$C$4*L12,0)+IF(O12>0,Rubric!$C$5*N12,0)+IF(Q12>0,Rubric!$C$6*P12,0)+IF(S12>0,Rubric!$C$7*R12,0))/(IF(K12>0,Rubric!$C$3,0)+IF(M12>0,Rubric!$C$4,0)+IF(O12>0,Rubric!$C$5,0)+IF(Q12>0,Rubric!$C$6,0)+IF(S12>0,Rubric!$C$7,0)),1)) -> 80.8 | X12: =IF(W12="","",IF(W12>=Rubric!$C$11,"A",IF(W12>=Rubric!$C$12,"B",IF(W12>=Rubric!$C$13,"C",IF(W12>=Rubric!$C$14,"D","F"))))) -> B | Y12: =IF(X12="","",IF(X12="A","Benchmark",IF(X12="B","Strong",IF(X12="C","Developing",IF(X12="D","Needs work","At risk"))))) -> Strong | Z12: =IF(COUNT(J12,L12,N12,P12,R12)=0,"",INDEX({"Findability","Catalog","Buy","Trust","Content"},MATCH(MIN(J12,L12,N12,P12,R12),CHOOSE({1,2,3,4,5},J12,L12,N12,P12,R12),0))) -> Content | AB12: Company is Bobby Moscow, LLC at 5799 Terex, Clarkston, MI 48346 (metro Detroit) per Privacy and Return pages; the site itself only names Detroit as its origin. Social profile links not present in fetched footer text on three pages.
A13: =IF(W13="","",RANK(W13,$W$2:$W$25,0)) -> 14 | B13: =IF(W13="","",1+COUNTIFS($D$2:$D$25,"Benchmark",$W$2:$W$25,">"&W13)) -> 12 | C13: English Gardens | D13: Benchmark | E13: Retail chain | F13: WooCommerce | G13: Dearborn Heights, MI | H13: https://www.englishgardens.com | I13: 2026-09-28 | J13: =IFERROR(SUMIFS(Checks!$F$2:$F$1297,Checks!$A$2:$A$1297,$C13,Checks!$C$2:$C$1297,"F")/(2*COUNTIFS(Checks!$A$2:$A$1297,$C13,Checks!$C$2:$C$1297,"F",Checks!$F$2:$F$1297,">=0")),"") -> 0.85714286 | K13: =COUNTIFS(Checks!$A$2:$A$1297,$C13,Checks!$C$2:$C$1297,"F",Checks!$F$2:$F$1297,">=0") -> 7 | L13: =IFERROR(SUMIFS(Checks!$F$2:$F$1297,Checks!$A$2:$A$1297,$C13,Checks!$C$2:$C$1297,"C")/(2*COUNTIFS(Checks!$A$2:$A$1297,$C13,Checks!$C$2:$C$1297,"C",Checks!$F$2:$F$1297,">=0")),"") -> 0.625 | M13: =COUNTIFS(Checks!$A$2:$A$1297,$C13,Checks!$C$2:$C$1297,"C",Checks!$F$2:$F$1297,">=0") -> 8 | N13: =IFERROR(SUMIFS(Checks!$F$2:$F$1297,Checks!$A$2:$A$1297,$C13,Checks!$C$2:$C$1297,"B")/(2*COUNTIFS(Checks!$A$2:$A$1297,$C13,Checks!$C$2:$C$1297,"B",Checks!$F$2:$F$1297,">=0")),"") -> 0.75 | O13: =COUNTIFS(Checks!$A$2:$A$1297,$C13,Checks!$C$2:$C$1297,"B",Checks!$F$2:$F$1297,">=0") -> 4 | P13: =IFERROR(SUMIFS(Checks!$F$2:$F$1297,Checks!$A$2:$A$1297,$C13,Checks!$C$2:$C$1297,"T")/(2*COUNTIFS(Checks!$A$2:$A$1297,$C13,Checks!$C$2:$C$1297,"T",Checks!$F$2:$F$1297,">=0")),"") -> 0.75 | Q13: =COUNTIFS(Checks!$A$2:$A$1297,$C13,Checks!$C$2:$C$1297,"T",Checks!$F$2:$F$1297,">=0") -> 4 | R13: =IFERROR(SUMIFS(Checks!$F$2:$F$1297,Checks!$A$2:$A$1297,$C13,Checks!$C$2:$C$1297,"N")/(2*COUNTIFS(Checks!$A$2:$A$1297,$C13,Checks!$C$2:$C$1297,"N",Checks!$F$2:$F$1297,">=0")),"") -> 1 | S13: =COUNTIFS(Checks!$A$2:$A$1297,$C13,Checks!$C$2:$C$1297,"N",Checks!$F$2:$F$1297,">=0") -> 3 | T13: =K13+M13+O13+Q13+S13 -> 26 | U13: =T13/29 -> 0.89655172 | V13: =IF(T13>=26,"High",IF(T13>=20,"Medium","Low")) -> High | W13: =IF((IF(K13>0,Rubric!$C$3,0)+IF(M13>0,Rubric!$C$4,0)+IF(O13>0,Rubric!$C$5,0)+IF(Q13>0,Rubric!$C$6,0)+IF(S13>0,Rubric!$C$7,0))=0,"",ROUND(100*(IF(K13>0,Rubric!$C$3*J13,0)+IF(M13>0,Rubric!$C$4*L13,0)+IF(O13>0,Rubric!$C$5*N13,0)+IF(Q13>0,Rubric!$C$6*P13,0)+IF(S13>0,Rubric!$C$7*R13,0))/(IF(K13>0,Rubric!$C$3,0)+IF(M13>0,Rubric!$C$4,0)+IF(O13>0,Rubric!$C$5,0)+IF(Q13>0,Rubric!$C$6,0)+IF(S13>0,Rubric!$C$7,0)),1)) -> 76.4 | X13: =IF(W13="","",IF(W13>=Rubric!$C$11,"A",IF(W13>=Rubric!$C$12,"B",IF(W13>=Rubric!$C$13,"C",IF(W13>=Rubric!$C$14,"D","F"))))) -> B | Y13: =IF(X13="","",IF(X13="A","Benchmark",IF(X13="B","Strong",IF(X13="C","Developing",IF(X13="D","Needs work","At risk"))))) -> Strong | Z13: =IF(COUNT(J13,L13,N13,P13,R13)=0,"",INDEX({"Findability","Catalog","Buy","Trust","Content"},MATCH(MIN(J13,L13,N13,P13,R13),CHOOSE({1,2,3,4,5},J13,L13,N13,P13,R13),0))) -> Catalog | AB13: WooCommerce + Elementor 4.2.4 + Yoast. Corporate office page confirms 22650 Ford Rd, Dearborn Heights.
... A22: =IF(W22="","",RANK(W22,$W$2:$W$25,0)) -> 24 | B22: =IF(W22="","",1+COUNTIFS($D$2:$D$25,"Benchmark",$W$2:$W$25,">"&W22)) -> 21 | C22: Sun Valley Foods | D22: Benchmark | E22: Wholesale / B2B | F22: Custom | G22: Detroit, MI | H22: https://www.sunvalleyfoods.com | I22: 2026-09-28 | J22: =IFERROR(SUMIFS(Checks!$F$2:$F$1297,Checks!$A$2:$A$1297,$C22,Checks!$C$2:$C$1297,"F")/(2*COUNTIFS(Checks!$A$2:$A$1297,$C22,Checks!$C$2:$C$1297,"F",Checks!$F$2:$F$1297,">=0")),"") -> 0.64285714 | K22: =COUNTIFS(Checks!$A$2:$A$1297,$C22,Checks!$C$2:$C$1297,"F",Checks!$F$2:$F$1297,">=0") -> 7 | L22: =IFERROR(SUMIFS(Checks!$F$2:$F$1297,Checks!$A$2:$A$1297,$C22,Checks!$C$2:$C$1297,"C")/(2*COUNTIFS(Checks!$A$2:$A$1297,$C22,Checks!$C$2:$C$1297,"C",Checks!$F$2:$F$1297,">=0")),"") -> 0.0625 | M22: =COUNTIFS(Checks!$A$2:$A$1297,$C22,Checks!$C$2:$C$1297,"C",Checks!$F$2:$F$1297,">=0") -> 8 | N22: =IFERROR(SUMIFS(Checks!$F$2:$F$1297,Checks!$A$2:$A$1297,$C22,Checks!$C$2:$C$1297,"B")/(2*COUNTIFS(Checks!$A$2:$A$1297,$C22,Checks!$C$2:$C$1297,"B",Checks!$F$2:$F$1297,">=0")),"") -> 0.3 | O22: =COUNTIFS(Checks!$A$2:$A$1297,$C22,Checks!$C$2:$C$1297,"B",Checks!$F$2:$F$1297,">=0") -> 5 | P22: =IFERROR(SUMIFS(Checks!$F$2:$F$1297,Checks!$A$2:$A$1297,$C22,Checks!$C$2:$C$1297,"T")/(2*COUNTIFS(Checks!$A$2:$A$1297,$C22,Checks!$C$2:$C$1297,"T",Checks!$F$2:$F$1297,">=0")),"") -> 0.5 | Q22: =COUNTIFS(Checks!$A$2:$A$1297,$C22,Checks!$C$2:$C$1297,"T",Checks!$F$2:$F$1297,">=0") -> 5 | R22: =IFERROR(SUMIFS(Checks!$F$2:$F$1297,Checks!$A$2:$A$1297,$C22,Checks!$C$2:$C$1297,"N")/(2*COUNTIFS(Checks!$A$2:$A$1297,$C22,Checks!$C$2:$C$1297,"N",Checks!$F$2:$F$1297,">=0")),"") -> 0.16666667 | S22: =COUNTIFS(Checks!$A$2:$A$1297,$C22,Checks!$C$2:$C$1297,"N",Checks!$F$2:$F$1297,">=0") -> 3 | T22: =K22+M22+O22+Q22+S22 -> 28 | U22: =T22/29 -> 0.96551724 | V22: =IF(T22>=26,"High",IF(T22>=20,"Medium","Low")) -> High | W22: =IF((IF(K22>0,Rubric!$C$3,0)+IF(M22>0,Rubric!$C$4,0)+IF(O22>0,Rubric!$C$5,0)+IF(Q22>0,Rubric!$C$6,0)+IF(S22>0,Rubric!$C$7,0))=0,"",ROUND(100*(IF(K22>0,Rubric!$C$3*J22,0)+IF(M22>0,Rubric!$C$4*L22,0)+IF(O22>0,Rubric!$C$5*N22,0)+IF(Q22>0,Rubric!$C$6*P22,0)+IF(S22>0,Rubric!$C$7*R22,0))/(IF(K22>0,Rubric!$C$3,0)+IF(M22>0,Rubric!$C$4,0)+IF(O22>0,Rubric!$C$5,0)+IF(Q22>0,Rubric!$C$6,0)+IF(S22>0,Rubric!$C$7,0)),1)) -> 33.1 | X22: =IF(W22="","",IF(W22>=Rubric!$C$11,"A",IF(W22>=Rubric!$C$12,"B",IF(W22>=Rubric!$C$13,"C",IF(W22>=Rubric!$C$14,"D","F"))))) -> F | Y22: =IF(X22="","",IF(X22="A","Benchmark",IF(X22="B","Strong",IF(X22="C","Developing",IF(X22="D","Needs work","At risk"))))) -> At risk | Z22: =IF(COUNT(J22,L22,N22,P22,R22)=0,"",INDEX({"Findability","Catalog","Buy","Trust","Content"},MATCH(MIN(J22,L22,N22,P22,R22),CHOOSE({1,2,3,4,5},J22,L22,N22,P22,R22),0))) -> Catalog | AB22: Alternate used in place of UTN Wholesale. HQ is stated only on the Careers page ('equal opportunity employer based in Detroit Michigan'); no street address appears anywhere on the site. Ordering is restricted to existing customers via the /erp login.
A23: =IF(W23="","",RANK(W23,$W$2:$W$25,0)) -> 1 | B23: =IF(W23="","",1+COUNTIFS($D$2:$D$25,"Benchmark",$W$2:$W$25,">"&W23)) -> 1 | C23: Blueroot Health (storefront scored: Fairhaven Health) | D23: Target | E23: DTC brand | F23: Shopify | G23: Middletown, CT | H23: https://www.fairhavenhealth.com | I23: 2026-09-28 | J23: =IFERROR(SUMIFS(Checks!$F$2:$F$1297,Checks!$A$2:$A$1297,$C23,Checks!$C$2:$C$1297,"F")/(2*COUNTIFS(Checks!$A$2:$A$1297,$C23,Checks!$C$2:$C$1297,"F",Checks!$F$2:$F$1297,">=0")),"") -> 1 | K23: =COUNTIFS(Checks!$A$2:$A$1297,$C23,Checks!$C$2:$C$1297,"F",Checks!$F$2:$F$1297,">=0") -> 8 | L23: =IFERROR(SUMIFS(Checks!$F$2:$F$1297,Checks!$A$2:$A$1297,$C23,Checks!$C$2:$C$1297,"C")/(2*COUNTIFS(Checks!$A$2:$A$1297,$C23,Checks!$C$2:$C$1297,"C",Checks!$F$2:$F$1297,">=0")),"") -> 1 | M23: =COUNTIFS(Checks!$A$2:$A$1297,$C23,Checks!$C$2:$C$1297,"C",Checks!$F$2:$F$1297,">=0") -> 8 | N23: =IFERROR(SUMIFS(Checks!$F$2:$F$1297,Checks!$A$2:$A$1297,$C23,Checks!$C$2:$C$1297,"B")/(2*COUNTIFS(Checks!$A$2:$A$1297,$C23,Checks!$C$2:$C$1297,"B",Checks!$F$2:$F$1297,">=0")),"") -> 1 | O23: =COUNTIFS(Checks!$A$2:$A$1297,$C23,Checks!$C$2:$C$1297,"B",Checks!$F$2:$F$1297,">=0") -> 5 | P23: =IFERROR(SUMIFS(Checks!$F$2:$F$1297,Checks!$A$2:$A$1297,$C23,Checks!$C$2:$C$1297,"T")/(2*COUNTIFS(Checks!$A$2:$A$1297,$C23,Checks!$C$2:$C$1297,"T",Checks!$F$2:$F$1297,">=0")),"") -> 0.9 | Q23: =COUNTIFS(Checks!$A$2:$A$1297,$C23,Checks!$C$2:$C$1297,"T",Checks!$F$2:$F$1297,">=0") -> 5 | R23: =IFERROR(SUMIFS(Checks!$F$2:$F$1297,Checks!$A$2:$A$1297,$C23,Checks!$C$2:$C$1297,"N")/(2*COUNTIFS(Checks!$A$2:$A$1297,$C23,Checks!$C$2:$C$1297,"N",Checks!$F$2:$F$1297,">=0")),"") -> 0.66666667 | S23: =COUNTIFS(Checks!$A$2:$A$1297,$C23,Checks!$C$2:$C$1297,"N",Checks!$F$2:$F$1297,">=0") -> 3 | T23: =K23+M23+O23+Q23+S23 -> 29 | U23: =T23/29 -> 1 | V23: =IF(T23>=26,"High",IF(T23>=20,"Medium","Low")) -> High | W23: =IF((IF(K23>0,Rubric!$C$3,0)+IF(M23>0,Rubric!$C$4,0)+IF(O23>0,Rubric!$C$5,0)+IF(Q23>0,Rubric!$C$6,0)+IF(S23>0,Rubric!$C$7,0))=0,"",ROUND(100*(IF(K23>0,Rubric!$C$3*J23,0)+IF(M23>0,Rubric!$C$4*L23,0)+IF(O23>0,Rubric!$C$5*N23,0)+IF(Q23>0,Rubric!$C$6*P23,0)+IF(S23>0,Rubric!$C$7*R23,0))/(IF(K23>0,Rubric!$C$3,0)+IF(M23>0,Rubric!$C$4,0)+IF(O23>0,Rubric!$C$5,0)+IF(Q23>0,Rubric!$C$6,0)+IF(S23>0,Rubric!$C$7,0)),1)) -> 95.2 | X23: =IF(W23="","",IF(W23>=Rubric!$C$11,"A",IF(W23>=Rubric!$C$12,"B",IF(W23>=Rubric!$C$13,"C",IF(W23>=Rubric!$C$14,"D","F"))))) -> A | Y23: =IF(X23="","",IF(X23="A","Benchmark",IF(X23="B","Strong",IF(X23="C","Developing",IF(X23="D","Needs work","At risk"))))) -> Benchmark | Z23: =IF(COUNT(J23,L23,N23,P23,R23)=0,"",INDEX({"Findability","Catalog","Buy","Trust","Content"},MATCH(MIN(J23,L23,N23,P23,R23),CHOOSE({1,2,3,4,5},J23,L23,N23,P23,R23),0))) -> Content | AA23: https://mousabatarseh.com/blueroot-review/ | AB23: All 40 Fairhaven fetches returned 200 via curl (no JS-render fallback needed). Review widgets (Stamped) and the Recharge subscription widget render client-side; counts were read from server-side badge attributes (data-reviews/data-rating) and SubscriptionWidgetConfig. Checkout was not entered; B3 is based on accelerated-checkout buttons on the PDP. Blog article pages were not fetched (per-store fetch cap), so N1 reflects the undated index only. Sister stores bariatricfusion.com, vitalnutrients.co and unjury.com were sampled (17 fetches total) for Part 2 cross-brand findings only and are not scored here. Health/medical claim language was deliberately not evaluated.
A24: =IF(W24="","",RANK(W24,$W$2:$W$25,0)) -> 21 | B24: =IF(W24="","",1+COUNTIFS($D$2:$D$25,"Benchmark",$W$2:$W$25,">"&W24)) -> 19 | C24: Federal Fluid Power, Inc. | D24: Target | E24: B2B distributor | F24: Magento | G24: Plymouth, MI | H24: https://federalfp.com | I24: 2026-09-28 | J24: =IFERROR(SUMIFS(Checks!$F$2:$F$1297,Checks!$A$2:$A$1297,$C24,Checks!$C$2:$C$1297,"F")/(2*COUNTIFS(Checks!$A$2:$A$1297,$C24,Checks!$C$2:$C$1297,"F",Checks!$F$2:$F$1297,">=0")),"") -> 0.75 | K24: =COUNTIFS(Checks!$A$2:$A$1297,$C24,Checks!$C$2:$C$1297,"F",Checks!$F$2:$F$1297,">=0") -> 8 | L24: =IFERROR(SUMIFS(Checks!$F$2:$F$1297,Checks!$A$2:$A$1297,$C24,Checks!$C$2:$C$1297,"C")/(2*COUNTIFS(Checks!$A$2:$A$1297,$C24,Checks!$C$2:$C$1297,"C",Checks!$F$2:$F$1297,">=0")),"") -> 0.625 | M24: =COUNTIFS(Checks!$A$2:$A$1297,$C24,Checks!$C$2:$C$1297,"C",Checks!$F$2:$F$1297,">=0") -> 8 | N24: =IFERROR(SUMIFS(Checks!$F$2:$F$1297,Checks!$A$2:$A$1297,$C24,Checks!$C$2:$C$1297,"B")/(2*COUNTIFS(Checks!$A$2:$A$1297,$C24,Checks!$C$2:$C$1297,"B",Checks!$F$2:$F$1297,">=0")),"") -> 0.4 | O24: =COUNTIFS(Checks!$A$2:$A$1297,$C24,Checks!$C$2:$C$1297,"B",Checks!$F$2:$F$1297,">=0") -> 5 | P24: =IFERROR(SUMIFS(Checks!$F$2:$F$1297,Checks!$A$2:$A$1297,$C24,Checks!$C$2:$C$1297,"T")/(2*COUNTIFS(Checks!$A$2:$A$1297,$C24,Checks!$C$2:$C$1297,"T",Checks!$F$2:$F$1297,">=0")),"") -> 0.7 | Q24: =COUNTIFS(Checks!$A$2:$A$1297,$C24,Checks!$C$2:$C$1297,"T",Checks!$F$2:$F$1297,">=0") -> 5 | R24: =IFERROR(SUMIFS(Checks!$F$2:$F$1297,Checks!$A$2:$A$1297,$C24,Checks!$C$2:$C$1297,"N")/(2*COUNTIFS(Checks!$A$2:$A$1297,$C24,Checks!$C$2:$C$1297,"N",Checks!$F$2:$F$1297,">=0")),"") -> 0.5 | S24: =COUNTIFS(Checks!$A$2:$A$1297,$C24,Checks!$C$2:$C$1297,"N",Checks!$F$2:$F$1297,">=0") -> 3 | T24: =K24+M24+O24+Q24+S24 -> 29 | U24: =T24/29 -> 1 | V24: =IF(T24>=26,"High",IF(T24>=20,"Medium","Low")) -> High | W24: =IF((IF(K24>0,Rubric!$C$3,0)+IF(M24>0,Rubric!$C$4,0)+IF(O24>0,Rubric!$C$5,0)+IF(Q24>0,Rubric!$C$6,0)+IF(S24>0,Rubric!$C$7,0))=0,"",ROUND(100*(IF(K24>0,Rubric!$C$3*J24,0)+IF(M24>0,Rubric!$C$4*L24,0)+IF(O24>0,Rubric!$C$5*N24,0)+IF(Q24>0,Rubric!$C$6*P24,0)+IF(S24>0,Rubric!$C$7*R24,0))/(IF(K24>0,Rubric!$C$3,0)+IF(M24>0,Rubric!$C$4,0)+IF(O24>0,Rubric!$C$5,0)+IF(Q24>0,Rubric!$C$6,0)+IF(S24>0,Rubric!$C$7,0)),1)) -> 61 | X24: =IF(W24="","",IF(W24>=Rubric!$C$11,"A",IF(W24>=Rubric!$C$12,"B",IF(W24>=Rubric!$C$13,"C",IF(W24>=Rubric!$C$14,"D","F"))))) -> C | Y24: =IF(X24="","",IF(X24="A","Benchmark",IF(X24="B","Strong",IF(X24="C","Developing",IF(X24="D","Needs work","At risk"))))) -> Developing | Z24: =IF(COUNT(J24,L24,N24,P24,R24)=0,"",INDEX({"Findability","Catalog","Buy","Trust","Content"},MATCH(MIN(J24,L24,N24,P24,R24),CHOOSE({1,2,3,4,5},J24,L24,N24,P24,R24),0))) -> Buy | AA24: https://mousabatarseh.com/federal-fluid-power-review/ | AB24: All pages fetched with curl (no 403/429). PDPs are server-rendered except the Hyva gallery/alt binding. Sitemap totals: only files 001, 005 and 009 of 9 were downloaded (54,496 URLs); the other six were not fetched to stay within the fetch cap, so site-wide figures are extrapolations from those three. Indeed job page could not be retrieved (WebFetch of the jk URL returned a different expired posting; Indeed MCP rate-limited), so posting text comes from the target brief. patriothyd.com is the same Magento install (same static version 1789741354, identical robots.txt listing both sitemaps) with the same SKUs, prices and copy; 2/2 sampled SKUs exist on both domains with self-referencing canonicals.
A25: =IF(W25="","",RANK(W25,$W$2:$W$25,0)) -> 13 | B25: =IF(W25="","",1+COUNTIFS($D$2:$D$25,"Benchmark",$W$2:$W$25,">"&W25)) -> 12 | C25: Royal Apparel, Inc. | D25: Target | E25: Manufacturer (USA-made blank apparel; wholesale B2B + retail + promo channels) | F25: Custom (WAM / liveb2b CGI templates) | G25: Hauppauge, NY | H25: https://www.royalapparel.net | I25: 2026-09-28 | J25: =IFERROR(SUMIFS(Checks!$F$2:$F$1297,Checks!$A$2:$A$1297,$C25,Checks!$C$2:$C$1297,"F")/(2*COUNTIFS(Checks!$A$2:$A$1297,$C25,Checks!$C$2:$C$1297,"F",Checks!$F$2:$F$1297,">=0")),"") -> 0.6875 | K25: =COUNTIFS(Checks!$A$2:$A$1297,$C25,Checks!$C$2:$C$1297,"F",Checks!$F$2:$F$1297,">=0") -> 8 | L25: =IFERROR(SUMIFS(Checks!$F$2:$F$1297,Checks!$A$2:$A$1297,$C25,Checks!$C$2:$C$1297,"C")/(2*COUNTIFS(Checks!$A$2:$A$1297,$C25,Checks!$C$2:$C$1297,"C",Checks!$F$2:$F$1297,">=0")),"") -> 0.875 | M25: =COUNTIFS(Checks!$A$2:$A$1297,$C25,Checks!$C$2:$C$1297,"C",Checks!$F$2:$F$1297,">=0") -> 8 | N25: =IFERROR(SUMIFS(Checks!$F$2:$F$1297,Checks!$A$2:$A$1297,$C25,Checks!$C$2:$C$1297,"B")/(2*COUNTIFS(Checks!$A$2:$A$1297,$C25,Checks!$C$2:$C$1297,"B",Checks!$F$2:$F$1297,">=0")),"") -> 0.7 | O25: =COUNTIFS(Checks!$A$2:$A$1297,$C25,Checks!$C$2:$C$1297,"B",Checks!$F$2:$F$1297,">=0") -> 5 | P25: =IFERROR(SUMIFS(Checks!$F$2:$F$1297,Checks!$A$2:$A$1297,$C25,Checks!$C$2:$C$1297,"T")/(2*COUNTIFS(Checks!$A$2:$A$1297,$C25,Checks!$C$2:$C$1297,"T",Checks!$F$2:$F$1297,">=0")),"") -> 0.9 | Q25: =COUNTIFS(Checks!$A$2:$A$1297,$C25,Checks!$C$2:$C$1297,"T",Checks!$F$2:$F$1297,">=0") -> 5 | R25: =IFERROR(SUMIFS(Checks!$F$2:$F$1297,Checks!$A$2:$A$1297,$C25,Checks!$C$2:$C$1297,"N")/(2*COUNTIFS(Checks!$A$2:$A$1297,$C25,Checks!$C$2:$C$1297,"N",Checks!$F$2:$F$1297,">=0")),"") -> 0.66666667 | S25: =COUNTIFS(Checks!$A$2:$A$1297,$C25,Checks!$C$2:$C$1297,"N",Checks!$F$2:$F$1297,">=0") -> 3 | T25: =K25+M25+O25+Q25+S25 -> 29 | U25: =T25/29 -> 1 | V25: =IF(T25>=26,"High",IF(T25>=20,"Medium","Low")) -> High | W25: =IF((IF(K25>0,Rubric!$C$3,0)+IF(M25>0,Rubric!$C$4,0)+IF(O25>0,Rubric!$C$5,0)+IF(Q25>0,Rubric!$C$6,0)+IF(S25>0,Rubric!$C$7,0))=0,"",ROUND(100*(IF(K25>0,Rubric!$C$3*J25,0)+IF(M25>0,Rubric!$C$4*L25,0)+IF(O25>0,Rubric!$C$5*N25,0)+IF(Q25>0,Rubric!$C$6*P25,0)+IF(S25>0,Rubric!$C$7*R25,0))/(IF(K25>0,Rubric!$C$3,0)+IF(M25>0,Rubric!$C$4,0)+IF(O25>0,Rubric!$C$5,0)+IF(Q25>0,Rubric!$C$6,0)+IF(S25>0,Rubric!$C$7,0)),1)) -> 77.6 | X25: =IF(W25="","",IF(W25>=Rubric!$C$11,"A",IF(W25>=Rubric!$C$12,"B",IF(W25>=Rubric!$C$13,"C",IF(W25>=Rubric!$C$14,"D","F"))))) -> B | Y25: =IF(X25="","",IF(X25="A","Benchmark",IF(X25="B","Strong",IF(X25="C","Developing",IF(X25="D","Needs work","At risk"))))) -> Strong | Z25: =IF(COUNT(J25,L25,N25,P25,R25)=0,"",INDEX({"Findability","Catalog","Buy","Trust","Content"},MATCH(MIN(J25,L25,N25,P25,R25),CHOOSE({1,2,3,4,5},J25,L25,N25,P25,R25),0))) -> Content | AA25: https://mousabatarseh.com/royal-apparel-review/ | AB25: Homepage / is a 515-byte static stub (meta refresh 0 + JS location.replace) to marketing.p, which 301s to /index; the stub has a self-canonical but no title/description, /index has title+description but no canonical. Category grids and PDP buy boxes are rendered client-side from inline JSON (prodJSON, $.wam.browse.init) so prices, colors, sizes and add-to-cart are absent from server HTML; pagination is hash-based (#page=2). Stock levels and add-to-cart could not be observed (no cart/login actions taken). /product/15250006/USA-Team-Beanie.html returns 200 with 'Product Not Found' (soft 404). LinkedIn job page blocked by robots for WebFetch; posting text taken from a mirror (thesocialmediaassociation.com). Fetch tally: ~39 GETs + 17 HEADs on the target, all logged in captures/index.txt.
C27: Benchmark average | W27: =ROUND(AVERAGEIF(D2:D25,"Benchmark",W2:W25),1) -> 75.9
C28: Benchmark median
C29: Rank on the benchmark = where a target would place among the 21 Michigan stores if it joined the index (1 = best). Targets are shaded blue and are not part of the public ShelfMark index.

Sheet Rubric
A1: Pillars & weights
A2: Pillar | B2: Name | C2: Weight | D2: Question the pillar answers
A3: F | B3: Findability | C3: 25 | D3: Can search engines and shoppers find the store and its products?
A4: C | B4: Catalog | C4: 30 | D4: Is the product data complete enough to sell from?
A5: B | B5: Buy | C5: 20 | D5: Is there a clear, trustworthy path from product to purchase?
A6: T | B6: Trust | C6: 15 | D6: Does the site prove there is a real, reachable business behind it?
A7: N | B7: Content | C7: 10 | D7: Does the store publish anything that helps a shopper decide?
B8: Total | C8: =SUM(C3:C7) -> 100
A10: Grade thresholds (score ≥)
A11: A | B11: Benchmark | C11: 85
A12: B | B12: Strong | C12: 70
A13: C | B13: Developing | C13: 55
A14: D | B14: Needs work | C14: 40
A15: F | B15: At risk | C15: below D
A16: Confidence: High = 26+ verified checks, Medium = 20–25, Low = under 20 (of 29).
A17: Deloitte Digital for Google, “Milliseconds Make Millions” (2020): a 0.1 s mobile speed improvement was associated with +8.4% retail conversion and +9.2% AOV (correlational). Core Web Vitals thresholds (web.dev): LCP ≤ 2.5 s, INP ≤ 200 ms, CLS ≤ 0.1. Used only as context — the rubric does not score speed.
A19: The 29 checks
A20: ID | B20: Check | C20: Pillar | D20: Scores 2 when… | E20: Scores 1 when… | F20: Scores 0 when… | H20: Published reference (where one exists)
A21: F1 | B21: HTTPS | C21: F | D21: Site serves on https (final URL https) | E21: Mixed / uncertain | F21: http only
A22: F2 | B22: robots.txt | C22: F | D22: Present, does not block products/categories, contains a Sitemap: line | E22: Present but no Sitemap line, or blocks something important | F22: Missing, or Disallow: / for everything | H22: Google Search Central — robots.txt introduction and the Sitemap directive · https://developers.google.com/search/docs/crawling-indexing/robots/intro
A23: F3 | B23: XML sitemap | C23: F | D23: Reachable and includes product/category (or article) URLs | E23: Reachable but thin / only static pages | F23: Not reachable | H23: Google Search Central — Build and submit a sitemap (50,000 URLs / 50 MB per file) · https://developers.google.com/search/docs/crawling-indexing/sitemaps/build-sitemap
A24: F4 | B24: Title tags | C24: F | D24: Homepage title is descriptive (brand + what/where) AND a sampled product title is unique and descriptive | E24: Present but generic / duplicated / templated | F24: Missing or just 'Home' | H24: Google Search Central — Influencing your title links in search results · https://developers.google.com/search/docs/appearance/title-link
A25: F5 | B25: Meta descriptions | C25: F | D25: Specific meta description on homepage AND on a sampled product page | E25: On one only, or templated / duplicated | F25: None | H25: Google Search Central — Control your snippets in search results (unique descriptions per page) · https://developers.google.com/search/docs/appearance/snippet
A26: F6 | B26: Canonical tags | C26: F | D26: Canonical present on homepage AND product page | E26: On one only | F26: None | H26: Google Search Central — Consolidate duplicate URLs with canonicals · https://developers.google.com/search/docs/crawling-indexing/consolidate-duplicate-urls
A27: F7 | B27: Structured data | C27: F | D27: Product/Breadcrumb schema evidence seen on product pages | E27: Partial evidence (e.g. breadcrumb schema only) | F27: None seen where expected | H27: Google Search Central — Product structured data (Offer, availability, aggregateRating rules) · https://developers.google.com/search/docs/appearance/structured-data/product
A28: F8 | B28: Clean URLs | C28: F | D28: Readable hyphenated product/category URLs, no session IDs | E28: Readable but awkward separators or numeric IDs appended | F28: Query-string-only product URLs | H28: Google Search Central — URL structure best practices · https://developers.google.com/search/docs/crawling-indexing/url-structure
A29: C1 | B29: Product titles | C29: C | D29: Descriptive and consistent (brand / type / size or count) | E29: Partially descriptive | F29: Vague / inconsistent
A30: C2 | B30: Descriptions | C30: C | D30: >=50 words of specific copy on both sampled products | E30: Short / boilerplate (<50 words) or only one product | F30: Missing
A31: C3 | B31: Imagery | C31: C | D31: >=2 images per product (gallery) with alt text | E31: One image, or missing alt text | F31: None / placeholder
A32: C4 | B32: Price & availability | C32: C | D32: Price AND stock state visible (B2B: clear 'login for pricing' plus how to get an account) | E32: Price only, no availability | F32: Neither / unclear
A33: C5 | B33: Variants & specs | C33: C | D33: Structured variant selectors and/or a spec table | E33: Variants only described in text | F33: None where expected
A34: C6 | B34: Taxonomy & breadcrumbs | C34: C | D34: Logical category tree (>=2 levels) AND breadcrumbs | E34: Categories but no breadcrumbs | F34: Flat / none
A35: C7 | B35: Filters & sort | C35: C | D35: Filters (price / type / attribute) AND sort on category pages | E35: Sort or pagination only | F35: None
A36: C8 | B36: Site search | C36: C | D36: Search box with a results page | E36: Search present but weak / unclear | F36: None
A37: B1 | B37: Primary CTA | C37: B | D37: Add to cart / order / request a quote prominent on product page AND homepage | E37: Present but buried | F37: No path to buy or enquire
A38: B2 | B38: Shipping & returns | C38: B | D38: Shipping AND returns info with specifics (thresholds, timelines) linked from product page or footer | E38: Generic policy page only | F38: None | H38: FTC Mail, Internet, or Telephone Order Merchandise Rule (shipping-time representations) · https://www.ftc.gov/legal-library/browse/rules/mail-internet-or-telephone-order-merchandise-rule
A39: B3 | B39: Checkout access | C39: B | D39: Guest checkout, or for B2B a clear become-a-customer application with steps | E39: Account required but sign-up exists | F39: No way to buy online
A40: B4 | B40: Merchandising | C40: B | D40: Homepage features collections / seasonal / new / best sellers with working links | E40: Static links only | F40: None
A41: B5 | B41: Trust signals | C41: B | D41: Product or store reviews PLUS guarantees / awards / secure badges | E41: One type only | F41: None
A42: T1 | B42: Contact | C42: T | D42: Phone + physical address + form or email | E42: Form or email only | F42: None
A43: T2 | B43: About | C43: T | D43: Substantial about / story page | E43: Brief | F43: None
A44: T3 | B44: Policies | C44: T | D44: Privacy AND terms (accessibility statement is a bonus) | E44: One | F44: None
A45: T4 | B45: Social | C45: T | D45: >=2 linked profiles | E45: One | F45: None
A46: T5 | B46: Accessibility basics | C46: T | D46: Skip link AND alt text on product images (or an accessibility statement) | E46: Some | F46: Images without alt and no skip link | H46: WCAG 2.2 — 1.1.1 Non-text Content and 2.4.1 Bypass Blocks · https://www.w3.org/TR/WCAG22/
A47: N1 | B47: Blog / news freshness | C47: N | D47: A dated post within the last 90 days | E47: Blog exists but stale or undated | F47: None | H47: Google Search Central — Creating helpful, reliable, people-first content · https://developers.google.com/search/docs/fundamentals/creating-helpful-content
A48: N2 | B48: Guides / FAQ | C48: N | D48: FAQ AND guides / recipes / how-tos | E48: FAQ only, or one guide | F48: None
A49: N3 | B49: Locations / where to buy | C49: N | D49: Locator or locations page with addresses & hours (B2B: service area / depots) | E49: A bare list | F49: None

Sheet Checks
A1: Store | B1: Source | C1: Pillar | D1: Check ID | E1: Check | F1: Score | G1: Evidence (what was observed, 2026-09-28)
A2: Stormy Kromer | B2: Benchmark | C2: F | D2: F1 | E2: HTTPS | F2: 2 | G2: Canonical https://www.stormykromer.com/; all pages fetched over https
A3: Stormy Kromer | B3: Benchmark | C3: F | D3: F2 | E3: robots.txt | F3: 2 | G3: Disallows only account/cart/checkout/search.php/admin; 'Sitemap: https://www.stormykromer.com/xmlsitemap.php' (GPTBot fully blocked)
A4: Stormy Kromer | B4: Benchmark | C4: F | D4: F3 | E4: XML sitemap | F4: 2 | G4: /sitemap.xml 404 but /xmlsitemap.php is an index with type=products, type=categories, type=pages, type=brands child sitemaps
A5: Stormy Kromer | B5: Benchmark | C5: F | D5: F4 | E5: Title tags | F5: 2 | G5: Home 'Rugged Wool Caps & Accessories Since 1903 | Stormy Kromer®'; PDP 'The Rancher Insulated Wool Cap | Stormy Kromer®'
A6: Stormy Kromer | B6: Benchmark | C6: F | D6: F5 | E6: Meta descriptions | F6: 2 | G6: Home: 'Stormy Kromer is the iconic wool winter cap with earflaps since 1903...'; PDP: 'Our fleece, wool and Thinsulate-lined Rancher Cap...'
A7: Stormy Kromer | B7: Benchmark | C7: F | D7: F6 | E7: Canonical tags | F7: 2 | G7: Canonicals on homepage, category (/mens/caps/ -> /mens-caps/) and both PDPs
A8: Stormy Kromer | B8: Benchmark | C8: F | D8: F7 | E8: Structured data | F8: 1 | G8: schema.org BreadcrumbList JSON-LD visible in /mens-caps/ HTML; Product schema not observed
A9: Stormy Kromer | B9: Benchmark | C9: F | D9: F8 | E9: Clean URLs | F9: 2 | G9: /the-rancher-cap/, /mens-caps/, /the-original-stormy-kromer-cap/ — clean hyphenated slugs
A10: Stormy Kromer | B10: Benchmark | C10: C | D10: C1 | E10: Product titles | F10: 2 | G10: 'The Original Stormy Kromer® Cap', 'The Rancher Cap', 'The Waxed Rancher Cap' — consistent name + type
A11: Stormy Kromer | B11: Benchmark | C11: C | D11: C2 | E11: Descriptions | F11: 2 | G11: Original ~115 words + DETAILS bullets; Rancher ~120 words ('For those seriously cold conditions...') + 6 product FAQs
A12: Stormy Kromer | B12: Benchmark | C12: C | D12: C3 | E12: Imagery | F12: 2 | G12: 8 and 6 gallery images; alt 'The Original Stormy Kromer Cap: a wool, six-panel winter cap with a pulldown earband, brim and tie'
A13: Stormy Kromer | B13: Benchmark | C13: C | D13: C4 | E13: Price & availability | F13: 2 | G13: 'Now: $65.00' with 'In Stock! Leaves Warehouse in 1-2 Days' on both PDPs
... A19: Stormy Kromer | B19: Benchmark | C19: B | D19: B2 | E19: Shipping & returns | F19: 2 | G19: 'Shipping $7.95 or Free Over $75' on PDP; returns 90 days, refund within four weeks, company pays only for its errors
A20: Stormy Kromer | B20: Benchmark | C20: B | D20: B3 | E20: Checkout access | F20: U | G20: checkout.php robots-blocked; guest checkout not observable from public pages
A21: Stormy Kromer | B21: Benchmark | C21: B | D21: B4 | E21: Merchandising | F21: 2 | G21: Homepage: 'SHOP BEST SELLERS' /best-sellers/, 'NEW SCHOOLS ADDED' /collegiate/, 'FOR THE FIELD' /hunting/, 'SUMMER SALE'
A22: Stormy Kromer | B22: Benchmark | C22: B | D22: B5 | E22: Trust signals | F22: 2 | G22: '5.0 Rating (1,412 reviews)' Original / '(603 reviews)' Rancher; 'Guaranteed for Life', 'No-Charge Insurance Policy'
A23: Stormy Kromer | B23: Benchmark | C23: T | D23: T1 | E23: Contact | F23: 2 | G23: /contact-us/: 888-455-2253, '1238 Wall Street, Ironwood, MI 49938', email, 7-field form, live chat button
A24: Stormy Kromer | B24: Benchmark | C24: T | D24: T2 | E24: About | F24: 2 | G24: /our-story/ ~800-900 words + Family/Values/Community/Manufacturing subpages; 'headquartered in Ironwood... Upper Peninsula'
A25: Stormy Kromer | B25: Benchmark | C25: T | D25: T3 | E25: Policies | F25: 2 | G25: /privacy-policy/, /terms-and-conditions/, plus /accessibility-statement/ citing WCAG 2.2 Level AA (bonus)
A26: Stormy Kromer | B26: Benchmark | C26: T | D26: T4 | E26: Social | F26: 2 | G26: Footer links facebook.com/StormyKromer, instagram.com/stormykromerofficial, youtube.com/user/StormyKromer, tiktok.com/@stormykromer, X
A27: Stormy Kromer | B27: Benchmark | C27: T | D27: T5 | E27: Accessibility basics | F27: 2 | G27: 'Skip to main content' (#main-content); descriptive product image alt text; accessibility statement page
A28: Stormy Kromer | B28: Benchmark | C28: N | D28: N1 | E28: Blog / news freshness | F28: 0 | G28: /blog/ renders a 'Blog' header with no posts; no blog URLs in xmlsitemap.php
A29: Stormy Kromer | B29: Benchmark | C29: N | D29: N2 | E29: Guides / FAQ | F29: 2 | G29: /faq/ ('HOW DO I FIGURE OUT MY CAP SIZE?'), /know-your-cap-size/ guide, sizing video + printable tape, per-product FAQs
A30: Stormy Kromer | B30: Benchmark | C30: N | D30: N3 | E30: Locations / where to buy | F30: 2 | G30: /factory-tour/: '1238 Wall Street, Ironwood, MI 49938', store hours 'Monday - Friday 9:00 a.m. to 5:00 p.m', Google Map; /retail-finder/
A31: Gardner-White Furniture | B31: Benchmark | C31: F | D31: F1 | E31: HTTPS | F31: 2 | G31: Homepage canonical https://www.gardner-white.com; every fetched page served over https
A32: Gardner-White Furniture | B32: Benchmark | C32: F | D32: F2 | E32: robots.txt | F32: 2 | G32: Sitemap: https://www.gardner-white.com/sitemap.xml; Disallow only /shop/*, /account/*, /in-store/*; Crawl-delay: 10
... A36: Gardner-White Furniture | B36: Benchmark | C36: F | D36: F6 | E36: Canonical tags | F36: 2 | G36: Canonical on home (https://www.gardner-white.com) and PDP (/product/195580-elliot-graphite-sofa)
A37: Gardner-White Furniture | B37: Benchmark | C37: F | D37: F7 | E37: Structured data | F37: U | G37: No structured-data evidence visible in fetched text
A38: Gardner-White Furniture | B38: Benchmark | C38: F | D38: F8 | E38: Clean URLs | F38: 1 | G38: /product/195580-elliot-graphite-sofa: readable slug but numeric ID prefixed; category URLs clean (/living-room/sofas)
A39: Gardner-White Furniture | B39: Benchmark | C39: C | D39: C1 | E39: Product titles | F39: 2 | G39: 'Elliot Graphite Sofa', 'Lawson Brown Reclining Sofa', 'Charlie 78 inch Cream Deep Seater Sofa' (name/color/type)
A40: Gardner-White Furniture | B40: Benchmark | C40: C | D40: C2 | E40: Descriptions | F40: 2 | G40: Elliot: description + 5 feature bullets + collection story (~150 words); Lawson ~60 words + collection copy
A41: Gardner-White Furniture | B41: Benchmark | C41: C | D41: C3 | E41: Imagery | F41: U | G41: Gallery/alt not in fetched HTML (client-rendered); 12 empty thumbnail list items seen on Lawson PDP
A42: Gardner-White Furniture | B42: Benchmark | C42: C | D42: C4 | E42: Price & availability | F42: 2 | G42: Elliot $1399.99 (was $1999.99) with 'Stocked:' field; Lawson $795.95 (was $1199.99); '$30 / Month' financing
A43: Gardner-White Furniture | B43: Benchmark | C43: C | D43: C5 | E43: Variants & specs | F43: 2 | G43: Spec table: Brand, Color/Finish, Material, Seat Height 19", W 92.25" x D 37" x H 33.5"; 'Color:' selector on Lawson
A44: Gardner-White Furniture | B44: Benchmark | C44: C | D44: C6 | E44: Taxonomy & breadcrumbs | F44: 2 | G44: Category breadcrumb 'Home > Living Room > Sofas'; 3-level tree in sitemap (/living-room/sectionals/components)
A45: Gardner-White Furniture | B45: Benchmark | C45: C | D45: C7 | E45: Filters & sort | F45: U | G45: Filters/sort not present in fetched category HTML (product grid renders client-side)
A46: Gardner-White Furniture | B46: Benchmark | C46: C | D46: C8 | E46: Site search | F46: 1 | G46: 'Search' toggle in header; results page not verified
A47: Gardner-White Furniture | B47: Benchmark | C47: B | D47: B1 | E47: Primary CTA | F47: U | G47: PDP shows price/financing but no add-to-cart label in fetched text; homepage has category/promo links only
A48: Gardner-White Furniture | B48: Benchmark | C48: B | D48: B2 | E48: Shipping & returns | F48: 2 | G48: Delivery: free weekday doorstep, white glove from $199.99, same-day; Returns: 7 days, 25% handling fee, 48h damage claims
A49: Gardner-White Furniture | B49: Benchmark | C49: B | D49: B3 | E49: Checkout access | F49: U | G49: Checkout not observed; Synchrony Pay Later 'offer available online only' implies online cart
A50: Gardner-White Furniture | B50: Benchmark | C50: B | D50: B4 | E50: Merchandising | F50: 2 | G50: Nav: New Arrivals, Bestsellers, Clearance, Sale, Back to School; featured Split Head Mattresses, ModularThree, Lighted Headboards
A51: Gardner-White Furniture | B51: Benchmark | C51: B | D51: B5 | E51: Trust signals | F51: 2 | G51: PDP 'Customer Reviews 4.0 (21)' and '4.7 (31)'; GW Mattress Pledge guarantee (/mattresses/pledge)
A52: Gardner-White Furniture | B52: Benchmark | C52: T | D52: T1 | E52: Contact | F52: 2 | G52: Privacy: 6500 E. 14 Mile Rd, Warren MI 48092, (586) 774-8853; terms: Auburn Hills addr; chat + service form + weborders@
A53: Gardner-White Furniture | B53: Benchmark | C53: T | D53: T2 | E53: About | F53: 1 | G53: About page ~75 words (founded Detroit 1912, family-owned); mostly links
A54: Gardner-White Furniture | B54: Benchmark | C54: T | D54: T3 | E54: Policies | F54: 2 | G54: Privacy policy + Terms & Conditions (/terms); bonus: Accessibility statement (WCAG 2.1 AA) and cookie policy
A55: Gardner-White Furniture | B55: Benchmark | C55: T | D55: T4 | E55: Social | F55: U | G55: No social profile URLs in fetched HTML on 4 pages (footer appears client-rendered)
A56: Gardner-White Furniture | B56: Benchmark | C56: T | D56: T5 | E56: Accessibility basics | F56: 2 | G56: 'Skip to Content' (#main) on every page + accessibility statement citing WCAG 2.1 AA
A57: Gardner-White Furniture | B57: Benchmark | C57: N | D57: N1 | E57: Blog / news freshness | F57: 2 | G57: news.gardner-white.com post 'Gardner White Hosts Laila Lockhart Kraner...' dated September 9, 2026
A58: Gardner-White Furniture | B58: Benchmark | C58: N | D58: N2 | E58: Guides / FAQ | F58: 2 | G58: FAQ page (/about/faq) + buying guides (/buying-guides/leather-buying-guide) + sofa FAQ block on category page
A59: Gardner-White Furniture | B59: Benchmark | C59: N | D59: N3 | E59: Locations / where to buy | F59: 2 | G59: /stores lists 30+ locations with street address + phone (e.g. 6500 E. 14 Mile Rd, Warren (586) 826-8300); hours in FAQ
A60: Cherry Republic | B60: Benchmark | C60: F | D60: F1 | E60: HTTPS | F60: 2 | G60: https://www.cherryrepublic.com/ with https canonical
A61: Cherry Republic | B61: Benchmark | C61: F | D61: F2 | E61: robots.txt | F61: 2 | G61: robots.txt allows /products/ and /collections/; 'Sitemap: https://www.cherryrepublic.com/sitemap.xml'
A62: Cherry Republic | B62: Benchmark | C62: F | D62: F3 | E62: XML sitemap | F62: 2 | G62: Sitemap index -> sitemap_products_1.xml, sitemap_collections_1.xml, sitemap_blogs_1.xml, sitemap_pages_1.xml
A63: Cherry Republic | B63: Benchmark | C63: F | D63: F4 | E63: Title tags | F63: 2 | G63: Home 'Michigan Cherries & Iconic Cherry Products | Cherry Republic'; PDP 'Dark Chocolate-Covered Cherries | Cherry Republic'
A64: Cherry Republic | B64: Benchmark | C64: F | D64: F5 | E64: Meta descriptions | F64: 2 | G64: Home 'Savor the taste of Northern Michigan...'; PDP 'Our dark chocolate-covered cherries blend rich cocoa...'
A65: Cherry Republic | B65: Benchmark | C65: F | D65: F6 | E65: Canonical tags | F65: 2 | G65: Canonical on home (/) and PDP (/products/dark-chocolate-covered-cherries-16oz)
A66: Cherry Republic | B66: Benchmark | C66: F | D66: F7 | E66: Structured data | F66: U | G66: No ld+json evidence in fetched text
A67: Cherry Republic | B67: Benchmark | C67: F | D67: F8 | E67: Clean URLs | F67: 2 | G67: /collections/chocolate, /products/amaretto-chocolate-covered-cherries - hyphenated, no IDs
A68: Cherry Republic | B68: Benchmark | C68: C | D68: C1 | E68: Product titles | F68: 2 | G68: 'Dark Chocolate Covered Cherries', 'Amaretto Chocolate Covered Cherries' - consistent; size via variant
A69: Cherry Republic | B69: Benchmark | C69: C | D69: C2 | E69: Descriptions | F69: 1 | G69: Dark Choc PDP ~200 words; Amaretto PDP only ~50 words (2 sentences)
A70: Cherry Republic | B70: Benchmark | C70: C | D70: C3 | E70: Imagery | F70: 1 | G70: Dark Choc: 6 images, an alt wrongly says 'Chocolate-covered almonds'; Amaretto: 3 images with no alt text
A71: Cherry Republic | B71: Benchmark | C71: C | D71: C4 | E71: Price & availability | F71: 1 | G71: Prices $15.95/$20.95 shown; no in-stock/sold-out state on PDP or collection
A72: Cherry Republic | B72: Benchmark | C72: C | D72: C5 | E72: Variants & specs | F72: 2 | G72: Size selector '7 oz. bag / 14 oz. bag'; Amaretto 'Size: 12 oz. bag'; nutrition label image
A73: Cherry Republic | B73: Benchmark | C73: C | D73: C6 | E73: Taxonomy & breadcrumbs | F73: 2 | G73: Nav Everything Cherry > 14 collections; breadcrumbs 'Home > Chocolate', 'Home > Dark Chocolate Covered Cherries'
A74: Cherry Republic | B74: Benchmark | C74: C | D74: C7 | E74: Filters & sort | F74: 1 | G74: 9 sort options (Featured, Best selling, Price low to high...) + pagination; no filters on /collections/chocolate
A75: Cherry Republic | B75: Benchmark | C75: C | D75: C8 | E75: Site search | F75: 2 | G75: /search?q=cherry+salsa returns '202 results found for "cherry salsa"'
A76: Cherry Republic | B76: Benchmark | C76: B | D76: B1 | E76: Primary CTA | F76: 2 | G76: 'Add to cart' on PDP; 'Shop Now' / 'Quick Shop' on homepage
A77: Cherry Republic | B77: Benchmark | C77: B | D77: B2 | E77: Shipping & returns | F77: 2 | G77: Shipping: $14.95 <$99, free $99-$250, 2-5 business days, cold packs; Bob's Guarantee: report damage within 24 hrs
A78: Cherry Republic | B78: Benchmark | C78: B | D78: B3 | E78: Checkout access | F78: U | G78: Checkout not fetchable (robots blocks /checkout); guest option not observable
A79: Cherry Republic | B79: Benchmark | C79: B | D79: B4 | E79: Merchandising | F79: 2 | G79: Home links Best Sellers, New & Seasonal, Free Ship Gifts, Gift Boxes, Chocolate collections
A80: Cherry Republic | B80: Benchmark | C80: B | D80: B5 | E80: Trust signals | F80: 2 | G80: Homepage 5-star testimonials + press quotes; '100% Satisfaction Guarantee'; USA Today Top Workplaces 2026
A81: Cherry Republic | B81: Benchmark | C81: T | D81: T1 | E81: Contact | F81: 2 | G81: (800) 206-6949, info@cherryrepublic.com, /pages/contact; HQ 6026 South Lake St, Glen Arbor, MI 49636
A82: Cherry Republic | B82: Benchmark | C82: T | D82: T2 | E82: About | F82: 2 | G82: /pages/about-cherry-republic ~350 words 'Since 1989' + separate /pages/our-history
A83: Cherry Republic | B83: Benchmark | C83: T | D83: T3 | E83: Policies | F83: 2 | G83: Privacy Policy (/policies/privacy-policy) + Terms of Service; /pages/accessibility too (bonus)
A84: Cherry Republic | B84: Benchmark | C84: T | D84: T4 | E84: Social | F84: 2 | G84: Facebook, Instagram, Pinterest, Twitter linked
A85: Cherry Republic | B85: Benchmark | C85: T | D85: T5 | E85: Accessibility basics | F85: 2 | G85: 'Skip to content' (#content); descriptive alts on home/collection images; /pages/accessibility
A86: Cherry Republic | B86: Benchmark | C86: N | D86: N1 | E86: Blog / news freshness | F86: 2 | G86: Up North Blog post 'Tart Cherries vs Sweet Cherries' shows 'Posted on September 10, 2026'
A87: Cherry Republic | B87: Benchmark | C87: N | D87: N2 | E87: Guides / FAQ | F87: 2 | G87: FAQ page (/pages/frequently-asked-questions) + Recipes blog + Gifting Guide page
A88: Cherry Republic | B88: Benchmark | C88: N | D88: N3 | E88: Locations / where to buy | F88: 1 | G88: Locations page lists 11 MI stores with addresses & phones but no hours
A89: American Spoon | B89: Benchmark | C89: F | D89: F1 | E89: HTTPS | F89: 2 | G89: https://spoon.com/ (www redirects to the apex domain, https)
A90: American Spoon | B90: Benchmark | C90: F | D90: F2 | E90: robots.txt | F90: 2 | G90: robots.txt allows /products/ & /collections/, blocks /cart, /checkout; 'Sitemap: https://spoon.com/sitemap.xml'
... A92: American Spoon | B92: Benchmark | C92: F | D92: F4 | E92: Title tags | F92: 1 | G92: Home <title> is just 'American Spoon'; PDP 'Sour Cherry Preserves - American Spoon'; collection title has a stray '*'
A93: American Spoon | B93: Benchmark | C93: F | D93: F5 | E93: Meta descriptions | F93: U | G93: WebFetch returned no <head> meta block for any spoon.com page; description not verifiable
A94: American Spoon | B94: Benchmark | C94: F | D94: F6 | E94: Canonical tags | F94: U | G94: Canonical not visible in fetched content (no meta block returned for spoon.com)
A95: American Spoon | B95: Benchmark | C95: F | D95: F7 | E95: Structured data | F95: U | G95: No ld+json evidence in fetched text
A96: American Spoon | B96: Benchmark | C96: F | D96: F8 | E96: Clean URLs | F96: 2 | G96: /products/sour-cherry-preserves, /collections/website-jam-preserves-nut-butters - hyphenated, no IDs
A97: American Spoon | B97: Benchmark | C97: C | D97: C1 | E97: Product titles | F97: 2 | G97: 'Sour Cherry Preserves', 'Red Haven Peach Preserves', 'Early Glow Strawberry Preserves' - variety + type; 9.5 oz shown
A98: American Spoon | B98: Benchmark | C98: C | D98: C2 | E98: Descriptions | F98: 2 | G98: ~150 words (Sour Cherry) and ~140 words (Red Haven Peach) incl. pairings and ingredients
A99: American Spoon | B99: Benchmark | C99: C | D99: C3 | E99: Imagery | F99: 2 | G99: 8 and 6 gallery images with alts like 'A jar of Sour Cherry Preserves', 'Peach cobbler with vanilla ice cream'
A100: American Spoon | B100: Benchmark | C100: C | D100: C4 | E100: Price & availability | F100: 2 | G100: $13.95 shown; 'Sold Out'/'Unavailable' states on collection cards and the PDP button
A101: American Spoon | B101: Benchmark | C101: C | D101: C5 | E101: Variants & specs | F101: 2 | G101: Ingredients 'Red tart cherries, sugar, lemon juice, pectin'; net weight '9.5 oz / 269 g'; single 'Default Title' variant
A102: American Spoon | B102: Benchmark | C102: C | D102: C6 | E102: Taxonomy & breadcrumbs | F102: 1 | G102: Nav Shop > 11 collections, Gifts > 9 collections; no breadcrumbs on collection or PDP
A103: American Spoon | B103: Benchmark | C103: C | D103: C7 | E103: Filters & sort | F103: 1 | G103: 'Sort by' + pagination (1, 2, 3, >) on /collections/all; no filters
A104: American Spoon | B104: Benchmark | C104: C | D104: C8 | E104: Site search | F104: 2 | G104: Header search box; /search?q=cherry -> '57 results' e.g. Fruit Perfect Sour Cherries $14.95
A105: American Spoon | B105: Benchmark | C105: B | D105: B1 | E105: Primary CTA | F105: 2 | G105: 'Add to Cart' on PDP; 'Shop Now' / 'Quick Shop' on homepage
A106: American Spoon | B106: Benchmark | C106: B | D106: B2 | E106: Shipping & returns | F106: 2 | G106: Shipping tiers $10 (<=$50) to $20 (>$175), '12 or more items ship for $12', regional transit 1-6 days; refund/replace policy
A107: American Spoon | B107: Benchmark | C107: B | D107: B3 | E107: Checkout access | F107: U | G107: Checkout not observable (robots blocks /checkout); no guest-checkout text on FAQ or customer-service pages
A108: American Spoon | B108: Benchmark | C108: B | D108: B4 | E108: Merchandising | F108: 2 | G108: Home: 'Stock Your Pantry', Fall Harvest, Bestsellers, New & Limited Edition; badges 'Best Seller'/'New'
A109: American Spoon | B109: Benchmark | C109: B | D109: B5 | E109: Trust signals | F109: 1 | G109: Homepage testimonials with star imagery (David C., Aimee G.); no guarantee/award/secure badges
...

Sheet Findings
A1: Store | B1: Source | C1: Score | D1: Type | E1: ID | F1: Finding | G1: Count / sample | H1: Maps to (posting duty) | I1: Why it matters | J1: Fix | K1: Evidence files (captures/) | L1: Pillar | M1: Status
A2: Stormy Kromer | B2: Benchmark | C2: =INDEX(Index!$W$2:$W$25,MATCH(A2,Index!$C$2:$C$25,0)) -> 95.1 | D2: Strength | E2: S1 | F2: PDPs are complete: 5.0-star ratings with 600-1,400 reviews, 'In Stock! Leaves Warehouse in 1-2 Days', size chart + calculator, product FAQs | L2: C | M2: Published
A3: Stormy Kromer | B3: Benchmark | C3: =INDEX(Index!$W$2:$W$25,MATCH(A3,Index!$C$2:$C$25,0)) -> 95.1 | D3: Strength | E3: S2 | F3: Findability is hand-tuned: unique titles/meta descriptions on home, category and PDPs, BreadcrumbList JSON-LD, clean slugs | L3: C | M3: Published
A4: Stormy Kromer | B4: Benchmark | C4: =INDEX(Index!$W$2:$W$25,MATCH(A4,Index!$C$2:$C$25,0)) -> 95.1 | D4: Strength | E4: S3 | F4: Trust stack: phone, street address, chat and form, WCAG 2.2 AA accessibility statement, factory store hours with map and retailer finder | L4: T | M4: Published
A5: Stormy Kromer | B5: Benchmark | C5: =INDEX(Index!$W$2:$W$25,MATCH(A5,Index!$C$2:$C$25,0)) -> 95.1 | D5: Fix | E5: F1 | F5: /blog/ is an empty shell with no posts and no sitemap entries — publish dated posts (care, sizing, factory stories) or remove the page | L5: N | M5: Published
A6: Stormy Kromer | B6: Benchmark | C6: =INDEX(Index!$W$2:$W$25,MATCH(A6,Index!$C$2:$C$25,0)) -> 95.1 | D6: Fix | E6: F2 | F6: PDP breadcrumbs follow seasonal collections ('Home > Collections > Father's Day Gifting > ...'); set a primary category so they read Men's > Caps | L6: C | M6: Published
A7: Stormy Kromer | B7: Benchmark | C7: =INDEX(Index!$W$2:$W$25,MATCH(A7,Index!$C$2:$C$25,0)) -> 95.1 | D7: Fix | E7: F3 | F7: Clean the PDP price template that prints blank 'Was:' and '(You save )' on full-price items, and add a /sitemap.xml redirect to /xmlsitemap.php | L7: F | M7: Published
A8: Gardner-White Furniture | B8: Benchmark | C8: =INDEX(Index!$W$2:$W$25,MATCH(A8,Index!$C$2:$C$25,0)) -> 93.8 | D8: Strength | E8: S1 | F8: PDPs carry full spec tables (dimensions, cushion construction, frame) with review counts (4.7/31) and monthly financing | L8: C | M8: Published
A9: Gardner-White Furniture | B9: Benchmark | C9: =INDEX(Index!$W$2:$W$25,MATCH(A9,Index!$C$2:$C$25,0)) -> 93.8 | D9: Strength | E9: S2 | F9: Delivery and returns are specific: free weekday doorstep delivery, same-day options, 7-day return window with the 25% fee stated | L9: B | M9: Published
A10: Gardner-White Furniture | B10: Benchmark | C10: =INDEX(Index!$W$2:$W$25,MATCH(A10,Index!$C$2:$C$25,0)) -> 93.8 | D10: Strength | E10: S3 | F10: Deep 3-level taxonomy with breadcrumbs, strong merchandising (Bestsellers/New/Clearance) and a news blog updated Sept 2026 | L10: C | M10: Published
A11: Gardner-White Furniture | B11: Benchmark | C11: =INDEX(Index!$W$2:$W$25,MATCH(A11,Index!$C$2:$C$25,0)) -> 93.8 | D11: Fix | E11: F1 | F11: Add a product sitemap covering all /product/ URLs and reference it from /sitemap.xml (only categories and guides are listed today) | L11: F | M11: Published
A12: Gardner-White Furniture | B12: Benchmark | C12: =INDEX(Index!$W$2:$W$25,MATCH(A12,Index!$C$2:$C$25,0)) -> 93.8 | D12: Fix | E12: F2 | F12: Server-render category product grids, filters/sort and the footer (privacy/terms/social links) - none appear in the served HTML | L12: T | M12: Published
A13: Gardner-White Furniture | B13: Benchmark | C13: =INDEX(Index!$W$2:$W$25,MATCH(A13,Index!$C$2:$C$25,0)) -> 93.8 | D13: Fix | E13: F3 | F13: Expand /about beyond ~75 words with the 1912 Detroit story, expose social links and phone in the footer HTML, drop Crawl-delay: 10 | L13: T | M13: Published
... A97: Lipari Foods | B97: Benchmark | C97: =INDEX(Index!$W$2:$W$25,MATCH(A97,Index!$C$2:$C$25,0)) -> 64.8 | D97: Fix | E97: F3 | F97: Add breadcrumbs, replace filename alt text ('ob-product-wholey-*') and add alt to category images, publish a prospective-customer FAQ (minimums, delivery days) and show dates on the News & Trends listing | L97: C | M97: Published
A98: Belle Tire | B98: Benchmark | C98: =INDEX(Index!$W$2:$W$25,MATCH(A98,Index!$C$2:$C$25,0)) -> 64.8 | D98: Strength | E98: S1 | F98: Clear conversion paths on the homepage: vehicle/size tire finder, 'Schedule Appointment', and manufacturer rebates with expiry dates | M98: Published
A99: Belle Tire | B99: Benchmark | C99: =INDEX(Index!$W$2:$W$25,MATCH(A99,Index!$C$2:$C$25,0)) -> 64.8 | D99: Strength | E99: S2 | F99: Strong guarantees: beat-any-competitor price promise, free lifetime tire maintenance, a price-match page and financing options | L99: C | M99: Published
A100: Belle Tire | B100: Benchmark | C100: =INDEX(Index!$W$2:$W$25,MATCH(A100,Index!$C$2:$C$25,0)) -> 64.8 | D100: Strength | E100: S3 | F100: Clean robots.txt with an 11-file sitemap index, per-vehicle finder URLs, and a privacy policy updated Jan 2026 with a contact email | L100: F | M100: Published
A101: Belle Tire | B101: Benchmark | C101: =INDEX(Index!$W$2:$W$25,MATCH(A101,Index!$C$2:$C$25,0)) -> 64.8 | D101: Fix | E101: F1 | F101: Server-render title, meta description and canonical tags - served HTML for home, /faq, /stores and tire PDPs has none; content is JS-only | L101: F | M101: Published
A102: Belle Tire | B102: Benchmark | C102: =INDEX(Index!$W$2:$W$25,MATCH(A102,Index!$C$2:$C$25,0)) -> 64.8 | D102: Fix | E102: F2 | F102: Clean sitemap-0.xml: remove 'https://test-page/' and 'page-not-found-error-rebate', and add lastmod to sitemap-index.xml | L102: F | M102: Published
A103: Belle Tire | B103: Benchmark | C103: =INDEX(Index!$W$2:$W$25,MATCH(A103,Index!$C$2:$C$25,0)) -> 64.8 | D103: Fix | E103: F3 | F103: Publish a real About page (/our-company is 404) and the Terms of Use the privacy policy cites; add a skip-to-content link | L103: T | M103: Published
A104: Germack Pistachio Company | B104: Benchmark | C104: =INDEX(Index!$W$2:$W$25,MATCH(A104,Index!$C$2:$C$25,0)) -> 63 | D104: Strength | E104: S1 | F104: Complete XML sitemap (~350 URLs) covering every product and category page | L104: F | M104: Published
A105: Germack Pistachio Company | B105: Benchmark | C105: =INDEX(Index!$W$2:$W$25,MATCH(A105,Index!$C$2:$C$25,0)) -> 63 | D105: Strength | E105: S2 | F105: 1,100-word founder story (1912) plus a QVC award badge, two Detroit addresses, hours, phone and a reCAPTCHA contact form | L105: T | M105: Published
A106: Germack Pistachio Company | B106: Benchmark | C106: =INDEX(Index!$W$2:$W$25,MATCH(A106,Index!$C$2:$C$25,0)) -> 63 | D106: Strength | E106: S3 | F106: Store locator with zip/city search, plus a blog of recipes and roasting how-tos | L106: N | M106: Published
A107: Germack Pistachio Company | B107: Benchmark | C107: =INDEX(Index!$W$2:$W$25,MATCH(A107,Index!$C$2:$C$25,0)) -> 63 | D107: Fix | E107: F1 | F107: Publish /robots.txt with 'Sitemap: https://www.germack.com/sitemap.xml' (currently 404), add canonical tags site-wide, refresh sitemap lastmod (all 2017) | L107: F | M107: Published
A108: Germack Pistachio Company | B108: Benchmark | C108: =INDEX(Index!$W$2:$W$25,MATCH(A108,Index!$C$2:$C$25,0)) -> 63 | D108: Fix | E108: F2 | F108: Replace the site-wide 'Germack Pistachio' <title> with unique titles (e.g. 'Dark Chocolate Almonds 12oz | Germack Pistachio Co., Detroit') and add missing PDP meta descriptions | L108: F | M108: Published
A109: Germack Pistachio Company | B109: Benchmark | C109: =INDEX(Index!$W$2:$W$25,MATCH(A109,Index!$C$2:$C$25,0)) -> 63 | D109: Fix | E109: F3 | F109: Add filters, sort and breadcrumbs to /shop,* category pages; add a shipping policy (rates, free-shipping threshold, transit time) linked from PDPs | L109: C | M109: Published
A110: Faygo Beverages | B110: Benchmark | C110: =INDEX(Index!$W$2:$W$25,MATCH(A110,Index!$C$2:$C$25,0)) -> 56.4 | D110: Strength | E110: S1 | F110: Clean WordPress brand site with canonicals, permissive robots + Yoast sitemap index, and a 1907-to-today history timeline | L110: F | M110: Published
... A121: Atlas Wholesale Food Co | B121: Benchmark | C121: =INDEX(Index!$W$2:$W$25,MATCH(A121,Index!$C$2:$C$25,0)) -> 54.4 | D121: Fix | E121: F3 | F121: Add Terms, a delivery/minimums policy and an FAQ; refresh In the News (newest item 2024) and rename the Jotform titled 'Clone of Atlas Wholesale Customer Registration Form' | L121: N | M121: Published
A122: Sun Valley Foods | B122: Benchmark | C122: =INDEX(Index!$W$2:$W$25,MATCH(A122,Index!$C$2:$C$25,0)) -> 33.1 | D122: Strength | E122: S1 | F122: Areas Served states the delivery footprint plainly: daily next-day delivery east to Port Huron, north to Bay City, west to Grand Rapids/Midland/Jackson, south to Northern Ohio | M122: Published
A123: Sun Valley Foods | B123: Benchmark | C123: =INDEX(Index!$W$2:$W$25,MATCH(A123,Index!$C$2:$C$25,0)) -> 33.1 | D123: Strength | E123: S2 | F123: Food Safety page documents HACCP planning and FDA/USDA/AIB/Michigan Dept of Education inspections — the credibility institutional buyers need | L123: C | M123: Published
A124: Sun Valley Foods | B124: Benchmark | C124: =INDEX(Index!$W$2:$W$25,MATCH(A124,Index!$C$2:$C$25,0)) -> 33.1 | D124: Strength | E124: S3 | F124: Clean HTTPS site with canonical tags and readable URLs on every page, plus dedicated market pages for K-12 and Healthcare | L124: F | M124: Published
A125: Sun Valley Foods | B125: Benchmark | C125: =INDEX(Index!$W$2:$W$25,MATCH(A125,Index!$C$2:$C$25,0)) -> 33.1 | D125: Fix | E125: F1 | F125: SEO basics: publish an XML sitemap (none at /sitemap.xml, /wp-sitemap.xml or /sitemap_index.xml) with a Sitemap: line in robots.txt, and rewrite the homepage title/meta ('Sun Valley Foods' / 'SunValleyFoods.com') to 'Institutional Foodservice Distributor, Detroit MI' | L125: F | M125: Published
A126: Sun Valley Foods | B126: Benchmark | C126: =INDEX(Index!$W$2:$W$25,MATCH(A126,Index!$C$2:$C$25,0)) -> 33.1 | D126: Fix | E126: F2 | F126: Add a Become a Customer page/application and a 'login for pricing' note beside Customer Orders; switch that link from http://www.sunvalleyfoods.com/erp to https and make it a prominent CTA on the homepage and Our Products | L126: B | M126: Published
A127: Sun Valley Foods | B127: Benchmark | C127: =INDEX(Index!$W$2:$W$25,MATCH(A127,Index!$C$2:$C$25,0)) -> 33.1 | D127: Fix | E127: F3 | F127: Put the Detroit street address, phone and hours on Contact Us and in the footer (only a CAPTCHA form exists), add social links and a skip link, and expand Our Products into category pages with sample items and pack sizes | L127: T | M127: Published
A128: Blueroot Health (storefront scored: Fairhaven Health) | B128: Target | C128: =INDEX(Index!$W$2:$W$25,MATCH(A128,Index!$C$2:$C$25,0)) -> 95.2 | D128: Strength | E128: S1 | F128: Clean technical SEO baseline: robots.txt with Sitemap line, sitemap index with 32 product + 42 collection URLs, canonicals and unique titles/meta descriptions on 20/20 sampled PDPs, Product+Offer+FAQPage JSON-LD on every PDP (captures/fh_pdp_sample_summary.json). | L128: F | M128: In review
A129: Blueroot Health (storefront scored: Fairhaven Health) | B129: Target | C129: =INDEX(Index!$W$2:$W$25,MATCH(A129,Index!$C$2:$C$25,0)) -> 95.2 | D129: Strength | E129: S2 | F129: Native Shopify Search & Discovery metafield filters (Gender, Life Stage, Health Benefit, Key Ingredients, Made Without, Product Form, Lifestyle, FSA/HSA) plus 9 sort options on collections and a working search results page (captures/fh_collections_female-fertility-supplements.html). | L129: C | M129: In review
A130: Blueroot Health (storefront scored: Fairhaven Health) | B130: Target | C130: =INDEX(Index!$W$2:$W$25,MATCH(A130,Index!$C$2:$C$25,0)) -> 95.2 | D130: Strength | E130: S3 | F130: Consistent PDP template on 20/20 sampled products: Key benefits / Ingredients / Suggested Use / Product Description / FAQ / Frequently Bought Together, Stamped review counts (up to 1,921), Recharge 10% subscribe widget, and prices that match products.json and collection cards on 20/20 (captures/fh_pdp_sample_summary.json). | L130: C | M130: In review
A131: Blueroot Health (storefront scored: Fairhaven Health) | B131: Target | C131: =INDEX(Index!$W$2:$W$25,MATCH(A131,Index!$C$2:$C$25,0)) -> 95.2 | D131: Fix | E131: F1 | F131: Footer 'Shop' nav and sitemap: remove or refill empty collections - /collections/shop-pregnancy ('0 products'), /collections/pregnancy-and-ovulation-tests ('No products found'), /collections/private (0 products) and /collections/ovulation-prediction (1 sold-out lubricant); set 'Pregnancy'/'Ovulation' footer links to live collections or unpublish them from the Online Store channel. | L131: B | M131: In review
A132: Blueroot Health (storefront scored: Fairhaven Health) | B132: Target | C132: =INDEX(Index!$W$2:$W$25,MATCH(A132,Index!$C$2:$C$25,0)) -> 95.2 | D132: Fix | E132: F2 | F132: Promotions: the '30% OFF LIMITED-TIME OFFER - SELECT SIZES - APPLIED IN CART' badge sits on 5 single-variant products (FertileCM, FertiliTea, Milkies, Complete Lactation Support, Menopause Multivitamin Essentials) while PDP/card/JSON-LD still show full price and compare_at_price is null on 32/32 products - use compare-at pricing or a Shopify Function discount that renders the sale price on card and PDP, and fix the 'select sizes' copy. | L132: C | M132: In review
A133: Blueroot Health (storefront scored: Fairhaven Health) | B133: Target | C133: =INDEX(Index!$W$2:$W$25,MATCH(A133,Index!$C$2:$C$25,0)) -> 95.2 | D133: Fix | E133: F3 | F133: Catalog data: fill product_type on 32/32 products (blank today vs 0/112 blank on bariatricfusion.com), normalize the 32 tags (three spellings of 'vaginal care', internal tags like exclude_rebuy/fam-fhpro-men mixed with merchandising tags), and move Supplement Facts from image-only (*_SFP.jpg on 17/20 PDPs) into a metafield rendered as an HTML table. | L133: C | M133: In review
A134: Blueroot Health (storefront scored: Fairhaven Health) | B134: Target | C134: =INDEX(Index!$W$2:$W$25,MATCH(A134,Index!$C$2:$C$25,0)) -> 95.2 | D134: Finding | E134: F1 | F134: Footer “Shop” links and the sitemap point at empty collections | G134: 3 of 8 footer collection links · 4 of 42 sitemap collections · 32 products vs 42 collections | H134: Collections & navigation QA | I134: The posting's first duty is collections, navigation and “routine QA checks for broken links and content discrepancies.” A footer link to zero products is the purchase-path dead end that role exists to catch. | J134: Unpublish shop-pregnancy, pregnancy-products, pregnancy-and-ovulation-tests, private, uncategorized and fairhaven-health from the Online Store channel so they leave the sitemap; retitle the survivors; repoint the footer “Pregnancy” link to /collections/prenatal and remove “Ovulation Prediction”; run the collection-health check below every Monday. | K134: fh_collections_shop-pregnancy.html, fh_collections_pregnancy-and-ovulation-tests.html, fh_collections_ovulation-prediction_products.json, fh_collections.json, fh_sitemap_collections_1.xml, fh_home.html | L134: B | M134: Prototyped
A135: Blueroot Health (storefront scored: Fairhaven Health) | B135: Target | C135: =INDEX(Index!$W$2:$W$25,MATCH(A135,Index!$C$2:$C$25,0)) -> 95.2 | D135: Finding | E135: F2 | F135: A sold-out product is the #2 item on All Products and in the search drawer sitewide | G135: position 2 of 32 on /collections/all · position 2 of 3 in “Trending Now” on 32 of 32 captured pages | H135: Sort defaults & discoverability | I135: The first screen of All Products and the search drawer are the two highest-traffic merchandising slots on the store, and both lead with something nobody can buy. | J135: Set All Products to Best selling (or manual with sold-out last); turn on “push sold-out to the bottom” in Search & Discovery; point the theme's Trending Now block at a curated collection; add the available flag from products.json to the weekly QA sheet so any sold-out SKU in a top-8 slot is flagged. | K135: fh_collections_all.html, fh_home.html, fh_pages_contactus.html, fh_products.json, vn_collections_all.html | L135: B | M135: Prototyped
A136: Blueroot Health (storefront scored: Fairhaven Health) | B136: Target | C136: =INDEX(Index!$W$2:$W$25,MATCH(A136,Index!$C$2:$C$25,0)) -> 95.2 | D136: Finding | E136: F3 | F136: “30% OFF – select sizes” badges on single-variant products while every price still shows full | G136: 5 of 32 products badged · 5 of 5 single-variant · 0 of 5 show a reduced price · 0 of 32 use compare-at pricing | H136: Promotions & pricing QA | I136: “Pricing issues” and “promotions” are explicit QA duties, and an Offer.price that differs from the checkout price is a Merchant Center and Shop app mismatch waiting to be flagged. | J136: Run the promotion as compare-at pricing on the affected variants (bulk editor) or as a Shopify Functions discount surfaced in the theme's price block so badge, price and JSON-LD agree; make the badge copy conditional on variant count; adopt a five-step promo launch check — badge → price display → JSON-LD → subscription price → cart total — on one badged PDP before go-live. | K136: fh_products_fertilecm-cervical-mucus-supplement.html, fh_collections_all.html, fh_products.json, bf_products.json, vn_products.json, unjury_products.json | L136: B | M136: Prototyped
A137: Blueroot Health (storefront scored: Fairhaven Health) | B137: Target | C137: =INDEX(Index!$W$2:$W$25,MATCH(A137,Index!$C$2:$C$25,0)) -> 95.2 | D137: Finding | E137: F4 | F137: Supplement Facts live only in JPGs; product_type and tags are unusable for merchandising | G137: facts panel image-only on 17 of 20 PDPs · Ingredients accordion ≤19 words on 15 of 20 · product_type blank on 32 of 32 · 32 tags on 32 products | H137: PDP content & product attributes | I137: Product attributes, SKU-level monitoring and feeds all key off product_type and tags, and text that exists only inside a JPG cannot be searched, filtered or read by a screen reader. | J137: Add a custom.supplement_facts metafield and render it as a table inside the Ingredients accordion (keep the image as a second view); set Shopify's standard Product Category plus a house product_type list on all 32 products via CSV; move internal flags to a custom.internal_flags metafield and collapse the three vaginal-care tags into one; a products.json diff before and after is the acceptance test. | K137: fh_pdp_sample_summary.json, fh_products_fh-pro-for-women.html, fh_products_milkies-nursing-postnatal-breastfeeding-multivitamin.html, fh_products.json, bf_products.json | L137: C | M137: Prototyped
A138: Blueroot Health (storefront scored: Fairhaven Health) | B138: Target | C138: =INDEX(Index!$W$2:$W$25,MATCH(A138,Index!$C$2:$C$25,0)) -> 95.2 | D138: Finding | E138: F5 | F138: Every sampled PDP title truncates in search; no rating or breadcrumb schema; no H1 on the homepage | G138: 20 of 20 titles at 73–91 characters · 13 of 20 descriptions end “Learn more…” · 0 of 20 with aggregateRating · 0 of 20 with BreadcrumbList · 20 of 20 og:image over http | H138: On-page SEO & digital-shelf scorecard | I138: The posting asks for on-page SEO, content scorecards and organic search visibility; these are the cheapest measurable wins on the digital shelf. | J138: Rewrite titles to ≤60 characters with the product first and the brand last (bulk editor or the search-engine-listing field) and replace the “Learn more…” tail; wrap the hero headline in an h1; enable Stamped's rich-snippet JSON-LD; add a BreadcrumbList snippet to main-product.liquid; set the social image URL to https. Track title length and schema presence per SKU in the weekly scorecard. | K138: fh_pdp_sample_summary.json, fh_home.html, fh_products_fh-pro-for-women.html, bf_products_glp-one.html, vn_products_glp-1-complete.html | L138: F | M138: Prototyped
A139: Blueroot Health (storefront scored: Fairhaven Health) | B139: Target | C139: =INDEX(Index!$W$2:$W$25,MATCH(A139,Index!$C$2:$C$25,0)) -> 95.2 | D139: Finding | E139: F6 | F139: Four stores, four conventions: policies, shipping promises and shared-SKU names diverge | G139: 4 themes · 4 policy-URL patterns · 3 free-shipping thresholds ($35 / $49 / $100) from one warehouse · 28 of 89 shared SKUs titled differently · 1 live “copy-of-” handle + 5 “-1” handles · 7 empty descriptions on Vital Nutrients | H139: Portfolio operating cadence | I139: The role is defined as “a documented, repeatable operating cadence across the portfolio.” These are the places where one owner and one checklist would show up immediately. | J139: Publish a one-page portfolio standard (policy handles, free-shipping copy, processing and transit language taken from the 3PL's real SLA, subscription discount) and align each store to it; keep a master SKU sheet (SKU → canonical title → price → subscription %) and reconcile bariatricfusion.com and unjury.com by CSV; rename the copy-of and -1 handles with 301 redirects; copy the kids-line section copy into body_html so Shop and Google feeds get a description. | K139: fh_pages_shipping-and-returns.html, bf_pages_shipping-policy.html, vn_pages_shipping-policy.html, unjury_pages_shipping-return-policy.html, bf_products.json, unjury_products.json, bf_products_copy-of-calcium-variety-pack.html, vn_products_tummy-troopers-probiotic.html | L139: T | M139: Prototyped
A140: Federal Fluid Power, Inc. | B140: Target | C140: =INDEX(Index!$W$2:$W$25,MATCH(A140,Index!$C$2:$C$25,0)) -> 61 | D140: Strength | E140: S1 | F140: Exact part-number search works: /catalogsearch/result/?q=FI-TE-04LLMK-W3-MS returns the one matching SKU with price and Add to Cart, and results pages are correctly noindexed | L140: C | M140: In review
A141: Federal Fluid Power, Inc. | B141: Target | C141: =INDEX(Index!$W$2:$W$25,MATCH(A141,Index!$C$2:$C$25,0)) -> 61 | D141: Strength | E141: S2 | F141: Product JSON-LD is unusually complete for a small distributor: Product, Offer with price/currency, shippingDetails (handling 2-5 days, $9.99) and MerchantReturnPolicy, plus BreadcrumbList on every PDP and category | L141: C | M141: In review
A142: Federal Fluid Power, Inc. | B142: Target | C142: =INDEX(Index!$W$2:$W$25,MATCH(A142,Index!$C$2:$C$25,0)) -> 61 | D142: Strength | E142: S3 | F142: The Engineering Toolbox (/engineering-toolbox/) is a genuine in-browser hydraulic calculator suite (cylinder force/area/speed, pumps, conversions) with 'Shop Cylinders' links back into the catalog | L142: C | M142: In review
A143: Federal Fluid Power, Inc. | B143: Target | C143: =INDEX(Index!$W$2:$W$25,MATCH(A143,Index!$C$2:$C$25,0)) -> 61 | D143: Fix | E143: F1 | F143: Give the ~20,000 products with no URL key a url_key (Magento admin bulk 'Update attributes' or import) so the sitemap stops listing /catalog/product/view/id/N/ URLs that robots.txt itself disallows; then regenerate the sitemap | L143: F | M143: In review
A144: Federal Fluid Power, Inc. | B144: Target | C144: =INDEX(Index!$W$2:$W$25,MATCH(A144,Index!$C$2:$C$25,0)) -> 61 | D144: Fix | E144: F2 | F144: Replace the single site-wide meta description on every PDP/CMS page with a Magento product meta template ({{name}} {{brand}} - Federal Fluid Power) and move thread size / port / material / pressure from the title string into filterable attributes | L144: C | M144: In review
A145: Federal Fluid Power, Inc. | B145: Target | C145: =INDEX(Index!$W$2:$W$25,MATCH(A145,Index!$C$2:$C$25,0)) -> 61 | D145: Fix | E145: F3 | F145: Fix the shared footer: change '© 2023 Patriot Hydraulics' to Federal Fluid Power 2026, point 'Shipping Policy'/'Return Policy' to real pages instead of /terms/, replace the two '#' links (Order History, Order Tracking), and set the header phone to 734-455-1722 instead of Patriot's 734-479-9641 | L145: B | M145: In review
A146: Federal Fluid Power, Inc. | B146: Target | C146: =INDEX(Index!$W$2:$W$25,MATCH(A146,Index!$C$2:$C$25,0)) -> 61 | D146: Finding | E146: F1 | F146: 37% of sitemap product URLs have no URL key and are blocked by robots.txt | G146: 20,242 of 54,496 URLs (37.1%) across the three sitemap files fetched · 3 of 3 sampled pages return 200 with a robots-blocked canonical | H146: ERP → Magento product data | I146: The role owns ERP-to-Magento product data, and a missing url_key on ~20,000 SKUs is exactly the kind of import-mapping gap that silently removes products from search. | J146: Filter the product grid for URL Key = empty, bulk-update (or re-import a CSV) with url_key = slugified name + SKU, reindex catalog_url_rewrite, regenerate the sitemap and verify no /catalog/product/view/ URLs remain. Keep the Disallow so the numeric duplicates never index. | K146: robots.txt, sitemap_005.xml, sitemap_009.xml, pdp_catalog_product_view_id_101454.html, pdp_catalog_product_view_id_97434.html, pdp_catalog_product_view_id_310140.html | L146: F | M146: Prototyped
A147: Federal Fluid Power, Inc. | B147: Target | C147: =INDEX(Index!$W$2:$W$25,MATCH(A147,Index!$C$2:$C$25,0)) -> 61 | D147: Finding | E147: F2 | F147: Specs live inside the title string; where attributes exist the values are dirty | G147: 18 of 19 PDPs with only Name / SKU / Weight / Brand · 0 of 19 with a thread, port, material or pressure attribute · Cylinders: 6 of 17 Bore values are inch-mark twins, 72 of 142 Bore×Stroke values are x/X twins, 2 values are Excel date serials | H147: Product attributes & layered navigation | I147: “Keep product data accurate” and “build listings with attributes” is the core of this role; these are the errors a buyer hits when filtering. | J147: Define thread_size, port_size, material, pressure_rating, pack_qty and mfr_part_number in an attribute set per product line; parse them out of existing names with a one-off script (the parser below is that script); normalize option values — strip inch marks, lowercase x, one unit convention — under Manage Options; re-export the cylinder CSV with text-formatted columns so 3/8 never becomes 44628 again. | K147: pdp_sample.csv, category_hydraulics-1_cylinders-1.html, pdp_bv3-04-npt.html, pdp_fi-ge-06llm6x1k-w3-ms-6010000421.html | L147: C | M147: Prototyped
A148: Federal Fluid Power, Inc. | B148: Target | C148: =INDEX(Index!$W$2:$W$25,MATCH(A148,Index!$C$2:$C$25,0)) -> 61 | D148: Finding | E148: F3 | F148: Price and availability contradict each other — the public symptoms of an unmapped ERP sync | G148: 9 of 19 PDPs are Request-Pricing-only, and 8 of those 9 declare InStock in schema · 1 of 19 prints $0.00 · Chairs & Creepers page 1: 20 of 20 unpriced · a $40,000–$50,000 price bucket on couplings | H148: Inventory & price sync | I148: The posting names the Magento-ERP integration and inventory accuracy; these are what a buyer, and Google, see when quantity and price fields do not map cleanly. | J148: Map ERP quantity and price into qty, is_in_stock and price on every sync run and key the RFQ module off is_salable; render Magento's stock-status block on PDPs; set Offer availability to OutOfStock or BackOrder (or drop the Offer) when the button is RFQ; add a sync alert for price = 0 or price > $10,000 on fittings. | K148: pdp_fi-ge-06llm6x1k-w3-ms-6010000421.html, pdp_catalog_product_view_id_101454.html, category_couplings.html, category_couplings_p2.html, category_chairs-and-creepers.html, pdp_sample.csv | L148: B | M148: Prototyped
A149: Federal Fluid Power, Inc. | B149: Target | C149: =INDEX(Index!$W$2:$W$25,MATCH(A149,Index!$C$2:$C$25,0)) -> 61 | D149: Finding | E149: F4 | F149: Manufacturer logos stand in for product photos on tens of thousands of SKUs | G149: 10 of 19 sampled PDPs show a supplier logo as the only image · sitemap-wide, 35,744 of 51,918 products (69%) share a generic first image · 512 have no image at all | H149: Product imagery | I149: The role writes copy, attributes and images for the store; a logo where the part should be is the single most visible content gap for a buyer comparing fittings. | J149: Pull supplier line-drawing and CAD sets (Stauff, Tompkins and Poclain publish them) and import by SKU via Import → Products with base_image, small_image and thumbnail; use a per-family drawing as the fallback instead of the logo; set a Magento image placeholder so the 512 image-less SKUs stop rendering blank; fix the tile alts. | K149: pdp_sample.csv, sitemap_001.xml, sitemap_005.xml, sitemap_009.xml, pdp_dshg-03-3c4-d24-n1-14-dir-valve-pilot-operated.html, homepage.html | L149: C | M149: Documented
A150: Federal Fluid Power, Inc. | B150: Target | C150: =INDEX(Index!$W$2:$W$25,MATCH(A150,Index!$C$2:$C$25,0)) -> 61 | D150: Finding | E150: F5 | F150: One meta description sitewide, code-only titles, and three URL layers for the same part | G150: 19 of 19 PDPs + 7 of 7 content pages share one description · 11 of 19 titles are the bare part code · 12 of 17 sitemap product URLs return 200 with a different canonical · 2,361 of 2,484 category URLs (95%) end in -1/-2/-3 · 58 homepage links into an alias category tree | H150: Content editing at catalog scale | I150: “Content editor” for a 52,000-SKU catalog means templates, not hand edits, and the crawl budget is currently spent on duplicates of the same part. | J150: Set product meta templates under Product Fields Auto-Generation ({{name}} | {{brand}} hydraulic {{category}} | Federal Fluid Power, and a description from name + brand + first spec); set Use Categories Path for Product URLs to No with permanent redirects on key change; run a URL-rewrite cleanup so old keys 301 instead of 200; relink the homepage grid to canonical category URLs; remove the second breadcrumb block from the Hyvä template. | K150: pdp_sample.csv, pdp_700018114.html, pdp_hp-10y-4-50-x10-00-yellow-hose-protector.html, category_couplings.html, homepage.html, sitemap_001.xml | L150: F | M150: Prototyped
A151: Federal Fluid Power, Inc. | B151: Target | C151: =INDEX(Index!$W$2:$W$25,MATCH(A151,Index!$C$2:$C$25,0)) -> 61 | D151: Finding | E151: F6 | F151: Federal's pages carry Patriot Hydraulics' copyright and phone number; policy links go to the wrong pages | G151: 2 wrong-brand strings on every page · Shipping and Return Policy both link to /terms/ · 2 “#” footer links · 6 test/junk pages in the sitemap · the same typo on 19 of 19 PDPs · 2 of 2 SKUs duplicated across both domains | H151: Multi-store hygiene | I151: These are the first things a customer sees, and each is a ten-minute fix inside Content → Blocks and Pages for someone who owns the multi-store setup. | J151: Scope the footer and header blocks to the Federal store view (copyright, phone); create real Shipping and Returns pages and relink the footer; disable the test pages and drop them from the sitemap; assign a proper no-route page; fix the typo in the PDP template; choose one canonical domain per SKU or noindex the Patriot copies. | K151: homepage.html, terms_shipping-policy.html, ffp-terms-conditions-of-sale.html, sitemap_009.xml, career.html, brand_patriot-hydraulics.html, patriot_homepage.html, patriot_pdp_fi-te-04llmk-w3-ms-6010000456.html | L151: T | M151: Prototyped
A152: Royal Apparel, Inc. | B152: Target | C152: =INDEX(Index!$W$2:$W$25,MATCH(A152,Index!$C$2:$C$25,0)) -> 77.6 | D152: Strength | E152: S1 | F152: Fresh homepage merchandising: the 4-slide hero uses creative dated 2026-09-09 to 2026-09-23 (e.g. /img/homepage_slider/B2B_S_USAManu_20260923.jpg) and every slide links to a live 200 page. | L152: B | M152: In review
A153: Royal Apparel, Inc. | B153: Target | C153: =INDEX(Index!$W$2:$W$25,MATCH(A153,Index!$C$2:$C$25,0)) -> 77.6 | D153: Strength | E153: S2 | F153: Deep, well-labelled product imagery: 5051 ships 107 alt-view images across 28 colors with alts like 'Unisex Short Sleeve Tee BLACK Back'; wrong product slugs and CGI product URLs 301 to the correct pretty URL. | L153: C | M153: In review
A154: Royal Apparel, Inc. | B154: Target | C154: =INDEX(Index!$W$2:$W$25,MATCH(A154,Index!$C$2:$C$25,0)) -> 77.6 | D154: Strength | E154: S3 | F154: Clear B2B commercial terms: public wholesale pricing, free freight >= $350 with the $9.95 handling fee stated, returns with RA number/20% restocking/10-day window, phone + HQ address + hours on /customer-service. | L154: T | M154: In review
A155: Royal Apparel, Inc. | B155: Target | C155: =INDEX(Index!$W$2:$W$25,MATCH(A155,Index!$C$2:$C$25,0)) -> 77.6 | D155: Fix | E155: F1 | F155: Add <link rel=canonical> (self-referencing pretty URL) to /index, every /Category/ page and every /product/ page, and 301 http:// and https://royalapparel.net to https://www.royalapparel.net (currently all return 200). | L155: F | M155: In review
A156: Royal Apparel, Inc. | B156: Target | C156: =INDEX(Index!$W$2:$W$25,MATCH(A156,Index!$C$2:$C$25,0)) -> 77.6 | D156: Fix | E156: F2 | F156: Rebuild sitemap.xml from the pretty URLs: drop the 408 redirecting catalog_browse.p entries, the cart/login/checkout/404 entries and the 200-status 'Product Not Found' products (e.g. /product/15250006/USA-Team-Beanie.html); add lastmod to the 248 product URLs. | L156: F | M156: In review
A157: Royal Apparel, Inc. | B157: Target | C157: =INDEX(Index!$W$2:$W$25,MATCH(A157,Index!$C$2:$C$25,0)) -> 77.6 | D157: Fix | E157: F3 | F157: Merge the two Product LD+JSON blocks on each PDP into one with brand, sku/mpn, image, offers.url, offers.availability (schema.org/InStock) and remove the hardcoded aggregateRating 5/326 unless it comes from real reviews; add BreadcrumbList. | L157: C | M157: In review
A158: Royal Apparel, Inc. | B158: Target | C158: =INDEX(Index!$W$2:$W$25,MATCH(A158,Index!$C$2:$C$25,0)) -> 77.6 | D158: Finding | E158: F1 | F158: The homepage is a meta-refresh stub; four hostnames answer 200 and no page carries a canonical | G158: 4 of 4 host/protocol variants return 200 · 0 of 24 HTML pages with a canonical · lowercase /category/men/ also 200 | H158: Technical SEO | I158: The posting owns technical SEO and GEO. With no canonicals and four live hostnames, link equity and AI-crawler citations split across duplicates, and the homepage's own signals point at an empty stub. | J158: At the web server: 301 http → https and non-www → www; serve the homepage at / and 301 /index to it (or the reverse — one of the two); delete the stub. In the layout template: a self-referencing canonical on every page built from the pretty path. Case-fold category paths and 301 the slash-less form. | K158: home-root.html, home-root-nonwww.html, redirect-chains.txt, home-marketing-p.html, index.txt | L158: F | M158: Prototyped
A159: Royal Apparel, Inc. | B159: Target | C159: =INDEX(Index!$W$2:$W$25,MATCH(A159,Index!$C$2:$C$25,0)) -> 77.6 | D159: Finding | E159: F2 | F159: The sitemap is 38% redirects, lists checkout and login pages, and serves dead products as 200 | G159: 408 of 1,063 URLs are redirecting CGI category links · 16 cart/login/checkout pages · 0 of 248 product URLs with lastmod · 3 of 20 sampled products dead or obsolete but 200 | H159: Deactivate discontinued items · crawlability | I159: “Deactivate discontinued items” is the posting's first merchandising duty; a sitemap that spends 40% of its entries on redirects and lists the checkout tells Google the catalog is unmaintained. | J159: Regenerate the sitemap nightly from the catalog: only www pretty URLs (/index, /Category/…/, /Accessory-Type/…/, /product/{style}/{slug}.html, landing pages) with a real lastmod per product; exclude obsolete items, Product-Not-Found styles and every CGI template; serve it on the www host and update robots.txt. Return 404 or 410 for retired styles and 301 obsolete styles to their replacement where the PDP already names one. | K159: sitemap.xml, sitemap-urls.txt, robots.txt, product-15250006.html, product-20055.html, product-32112.html, pdp-sample-analysis.json | L159: F | M159: Prototyped
A160: Royal Apparel, Inc. | B160: Target | C160: =INDEX(Index!$W$2:$W$25,MATCH(A160,Index!$C$2:$C$25,0)) -> 77.6 | D160: Finding | E160: F3 | F160: Product schema is split in two, blank on availability, and carries the same 5★ / 326-review rating on every product | G160: 19 of 19 PDPs with two Product blocks · 19 of 19 with Offer.availability “” · 19 of 19 identical aggregateRating 5 / 326 · 0 of 20 BreadcrumbList, og:image, GTIN or MPN · 150 of 150 color hexes set to FFFFFF | H160: Feeds & structured data | I160: The posting asks for feed optimization and marketplace product data. Google's product rich results need one Product with brand, offers.availability and an authentic rating; a sitewide fabricated review count is what gets Merchant Center listings disapproved. | J160: In the product template, output one Product: name, sku/mpn (the style code), brand (Royal Apparel, or Basic Supply Co. when the mill code is BSC), the image array, plain-text description, an AggregateOffer from the low/high wholesale price with availability derived from the same quantity the page already uses, no aggregateRating unless it comes from real reviews, plus BreadcrumbList and og:image. Fill hexColor from the swatch palette and export GTIN per SKU in the feed. | K160: product-5051.html, product-5001W.html, product-5051-prodJSON.json, pdp-sample-analysis.json | L160: F | M160: Prototyped
A161: Royal Apparel, Inc. | B161: Target | C161: =INDEX(Index!$W$2:$W$25,MATCH(A161,Index!$C$2:$C$25,0)) -> 77.6 | D161: Finding | E161: F4 | F161: GA4 receives products without names, views without currency and no list attribution | G161: 21 of 21 category impressions with blank item_name and item_brand · 20 of 20 view_item pushes without currency or brand · page-level push array-wrapped on every template · 0 view_item_list or select_item events anywhere | H161: Validate GA4 and tag-manager tracking | I161: The posting says “validate GA4 and tag-manager tracking” and build the dashboards. With these payloads, item reports show IDs without names, revenue-less views and no attribution for the merchandising the coordinator is meant to optimize. | J161: Change the page push to a plain object; emit view_item_list on listings with item_list_id, item_list_name and complete items (name from the description, brand from the mill code, numeric price, index) and select_item on click; send view_item with currency, value and item-level price, brand and variant; replace the UA-shaped related push with a second view_item_list; standardize add_to_cart on currency. Verify in GTM Preview and GA4 DebugView, then add a data-quality tile (name and price coverage) to the dashboard. | K161: home-marketing-p.html, category-men.html, product-5051.html, product-5001W.html, js-catalog_product.js | L161: C | M161: Prototyped
A162: Royal Apparel, Inc. | B162: Target | C162: =INDEX(Index!$W$2:$W$25,MATCH(A162,Index!$C$2:$C$25,0)) -> 77.6 | D162: Finding | E162: F5 | F162: Category grid: 21 of 136 Men's products in the HTML, $0.00 tiles, “New” on everything, Men = Unisex | G162: 21 of 136 products (15%) present in HTML · 3 of 21 tiles at $0.00 · 21 of 21 flagged new · position 1 is an imported tee · Men (136) = Unisex (136) · 90 of 359 images without alt | H162: Website merchandising | I162: Tagged product groups, sort order, deactivating items and category curation are the core of the posting, and the data shows the levers are not being used. | J162: Server-render the first page of cards with real pagination links and a canonical; give custom-dye programs a “Request pricing” tile instead of $0.00; reset isNew to a 60-day window from the street date; canonicalize Men to Unisex or curate a distinct Men's assortment; 301 the Face-Cover slug to /Category/Accessories/; pin Royal-made styles above Basic Supply Co. imports on USA-positioned categories and in style-number search. | K162: category-men.html, category-men-browse-data.json, category-face-cover-accessories.html, search-5051.html | L162: B | M162: Prototyped
A163: Royal Apparel, Inc. | B163: Target | C163: =INDEX(Index!$W$2:$W$25,MATCH(A163,Index!$C$2:$C$25,0)) -> 77.6 | D163: Finding | E163: F6 | F163: Size charts are images labelled “Pick your color”, no product video, a News page with no news, a footer link that 404s sitewide | G163: 18 chart images, 0 tables · 13 of 15 chart alts read “Pick your color” · 0 of 19 PDPs with video · 0 dated posts on /in-the-news · 1 footer link → 404 on every page · 38 of 38 image filenames are timestamps | H163: Content, photography, video | I163: An AI answer engine cannot read a size chart that is a JPEG labelled “Pick your color,” and a news page with no news undercuts the story the company is paying trade press to tell. | J163: Rebuild the size charts as HTML tables (one per fit, inch and cm) and surface the matching table in the PDP Specs tab; fix the 13 alts. Publish the three 2025–26 stories on /in-the-news with dates and NewsArticle schema, then a monthly cadence from new-style drops. Point Eco-Certifications at a real page or remove it. Shoot short colorway clips for the top 20 styles and set the video fields the template already reads. Name new uploads by style and color. | K163: product-specifications.html, in-the-news.html, home-marketing-p.html, pdp-sample-analysis.json, index.txt | L163: N | M163: Documented

Sheet Impact ledger
A1: # | B1: Project / employer | C1: What I did | D1: Before | E1: After / result | F1: Source of the number | G1: Confidence | H1: What would make it measured | I1: Résumé line it supports
A2: 1 | B2: Universal Wholesale & United Textile (2019–2024) | C2: Built and ran two storefronts in parallel (WooCommerce + Shopify); catalog maintained by bulk CSV | D2: — | E2: 14,000+ SKUs maintained: pricing, collections, categories, descriptions, images, SEO metadata | F2: Résumé; portfolio ‘Counted, not claimed’ tile (Universal Wholesale) | G2: Stated | H2: Export the product CSV row count from the store admin and date it | I2: Owned product setup and catalog data for 14,000+ SKUs
A3: 2 | B3: United Textile (Shopify) | C3: Moved the catalog from an offline inventory system into a new Shopify store | D3: 0 products online | E3: 1,000 products live in Shopify | F3: Portfolio tile (United Textile) | G3: Stated | H3: Shopify products export with the launch date | I3: Migrated 1,000 products from an offline inventory system into Shopify
A4: 3 | B4: Universal Wholesale / United Textile | C4: Technical and on-page SEO after the platform migration; redirects and URL structure kept intact | D4: Not ranking for target queries | E4: Google pages 1–2 for target queries within the first year | F4: Résumé (‘improved organic rankings to Google pages 1–2 within the first year’) | G4: Approximate | H4: Search Console query report screenshots before/after (if property access remains) — name the queries | I4: Took organic rankings to Google pages 1–2 within the first year
A5: 4 | B5: Universal Wholesale | C5: Led the RepZio B2B platform migration with redirect mapping | D5: Old platform URLs | E5: Migration completed with redirects mapped | F5: Résumé | G5: Stated | H5: Count of redirect rules in the map; 404 report after cut-over | I5: Managed redirects and URL structure through migrations; led the RepZio B2B migration
A6: 5 | B6: Wild Bill’s Tobacco (2024–2025) | C6: Administered two corporate sites and the wholesale B2B store; operated the catalog | D6: — | E6: ~9,000-product catalog operated: accuracy, pricing, descriptions, imagery | F6: Résumé | G6: Stated | H6: WooCommerce product count export, dated | I6: Operated a ~9,000-product wholesale catalog
A7: 6 | B7: The Deals Operating System (own build) | C7: Promotion-accuracy QA workbook + walkthrough for a multi-location retailer (modeled as Northgate Retail Group) | D7: Promotions checked by hand | E7: 16 checks every promotion passes before it reaches a menu | F7: Portfolio tile; The Lab | G7: Measured (the checks exist) | H7: Count of promotions run through the sheet and the errors it caught in one month | I7: Built a 16-check promotion QA system
A8: 7 | B8: ASAS Studio (own product) | C8: Elementor block library | D8: — | E8: 3,881 real Elementor blocks (asas.build) | F8: Portfolio tile — note: the master résumé says ‘4,038 Elementor templates’; reconcile to one number | G8: Measured | H8: Count from the ASAS database, dated | I8: Built ASAS Studio, a library of 3,881 Elementor blocks
A9: 8 | B9: Independent reviews (Sept 2026) | C9: Independent, evidence-backed storefront reviews with working prototypes, one per application | D9: 0 | E9: 22 reviews published on mousabatarseh.com/reviews (Sept 2026); DiaMedical USA answered one with a formal interview project and an onsite interview | F9: mousabatarseh.com/reviews; DiaMedical correspondence | G9: Measured (counts) / Stated (response) | H9: Log every reply per review on the Outreach sheet; report replies ÷ reviews monthly | I9: Published 22 independent storefront reviews; one led directly to an interview
A10: 9 | B10: ShelfMark — Michigan Storefront Benchmark (own build) | C10: Scored 21 Michigan storefronts on 29 public-page checks | D10: — | E10: 609 scored observations with evidence; live index + workbook | F10: ShelfMark workbook README | G10: Measured | H10: — | I10: Built ShelfMark, a 29-check storefront benchmark of 21 Michigan stores
A11: 10 | B11: Carhartt Reworked review (Sept 2026) | C11: Read the resale store’s full public feed | D11: — | E11: 3,545 listings and 124 collections read; 10 findings, 4 working fixes | F11: mousabatarseh.com/reworked-review | G11: Measured | H11: — | I11: Reviewed Carhartt Reworked end to end: 3,545 listings, 124 collections
A12: 11 | B12: Blueroot Health review (Sept 28, 2026) | C12: Four Shopify stores read with the engine | D12: — | E12: 397 products across four stores; six findings; Fairhaven scored 95/100 (would rank 1st of 21) | F12: targets/blueroot | G12: Measured | H12: — | I12: —
A13: 12 | B13: Royal Apparel review (Sept 28, 2026) | C13: Custom-platform B2B store read with the engine | D13: — | E13: 1,063 sitemap URLs classified; 0 of 24 pages with a canonical; six findings, five fixes | F13: targets/royal-apparel | G13: Measured | H13: — | I13: —
... A15: 14 | B15: PageSpeed Insights (a site he runs) | C15: Performance work on a production site | D15: — | E15: Near-perfect PSI scores (Performance, Accessibility, Best Practices, SEO) | F15: Own statement | G15: Approximate — site and date not recorded here | H15: Name the site; save the dated PSI report PDF next to this sheet | I15: Near-perfect Core Web Vitals on a production site
B17: Measured = a count or export exists. Stated = said on the résumé without an artifact. Approximate = a real outcome without a baseline. Only Measured rows go on the résumé as numbers; Stated rows are written as scope, not results.

Sheet Outreach
A1: Company | B1: Role | C1: Score | D1: The one finding in the message | E1: Contact | F1: Title | G1: Channel | H1: Status | I1: Sent | J1: Follow-up | K1: Reply | L1: Notes
A2: Blueroot Health (storefront scored: Fairhaven Health) | B2: DTC Operations Manager | C2: =INDEX(Index!$W$2:$W$25,MATCH(A2,Index!$C$2:$C$25,0)) -> 95.2 | D2: Footer “Shop” links and the sitemap point at empty collections | E2: Domenic DiSiena | F2: Head of eCommerce (per ZoomInfo; LinkedIn headline: Senior Ecommerce & Digital Executive) | G2: LinkedIn InMail | H2: Drafted
A3: Blueroot Health (storefront scored: Fairhaven Health) | B3: DTC Operations Manager | C3: =INDEX(Index!$W$2:$W$25,MATCH(A3,Index!$C$2:$C$25,0)) -> 95.2 | D3: Footer “Shop” links and the sitemap point at empty collections | E3: Erin Anthony | F3: Chief Marketing Officer | G3: LinkedIn connection note | H3: Drafted
A4: Federal Fluid Power, Inc. | B4: Full Stack IT Specialist, E-Commerce Developer & Content Editor | C4: =INDEX(Index!$W$2:$W$25,MATCH(A4,Index!$C$2:$C$25,0)) -> 61 | D4: 37% of sitemap product URLs have no URL key and are blocked by robots.txt | E4: Ryan Barringer | F4: President (BBB principal contact); Sales & Applications Engineer on LinkedIn | G4: Email + LinkedIn connection note | H4: Drafted
A5: Federal Fluid Power, Inc. | B5: Full Stack IT Specialist, E-Commerce Developer & Content Editor | C5: =INDEX(Index!$W$2:$W$25,MATCH(A5,Index!$C$2:$C$25,0)) -> 61 | D5: 37% of sitemap product URLs have no URL key and are blocked by robots.txt | E5: Mark Barringer | F5: General Manager | G5: LinkedIn connection note | H5: Drafted
A6: Royal Apparel, Inc. | B6: Digital Marketing & Ecommerce Coordinator | C6: =INDEX(Index!$W$2:$W$25,MATCH(A6,Index!$C$2:$C$25,0)) -> 77.6 | D6: The homepage is a meta-refresh stub; four hostnames answer 200 and no page carries a canonical | E6: Glen Brumer | F6: Sales Director | G6: LinkedIn InMail | H6: Drafted
A7: Royal Apparel, Inc. | B7: Digital Marketing & Ecommerce Coordinator | C7: =INDEX(Index!$W$2:$W$25,MATCH(A7,Index!$C$2:$C$25,0)) -> 77.6 | D7: The homepage is a meta-refresh stub; four hostnames answer 200 and no page carries a canonical | E7: Morey Mayeri | F7: Founder | G7: LinkedIn connection note | H7: Drafted
A9: One message per person, within 48 hours of applying: the private review link and ONE finding. Follow up once after 7 days, then move on. Log every reply.

Sheet Messages
B2: The notes that go with a review
B4: InMail to the hiring manager (≤120 words)
B5: Subject: [Company]'s storefront — one thing I found, and a full review
B6: Hi [First name] — I applied for the [Role] and, before I did, I read [store] the way the posting describes the job: [scope in a phrase, e.g. four stores, 397 products, no logins].
B7: One finding: [the count — e.g. 3 of the 8 footer Shop links open an empty collection]. The full review, with working fixes and the QA sheet, is here (private link): mousabatarseh.com/[path]/
B8: Everything comes from public pages and it opens with what the store does well. If it's useful, I'd welcome 20 minutes to walk through it. — Mousa Batarseh, Warren MI · hireme@mousabatarseh.com
B10: Connection note (≤300 characters)
B11: Hi [First name], I applied for [Company]'s [Role] and reviewed [store] first — [one count]. The review with working fixes: mousabatarseh.com/[path]/. Glad to connect. Mousa
B13: Email to a named person (when no LinkedIn route)
B14: Subject: [Role] application — a review of [store] to go with it
B15: Hi [First name],
B16: I applied for the [Role] on [date]. To show how I'd work rather than say it, I reviewed [store] from its public pages first: [scope]. It opens with three things the store does well, then [N] findings with counts, and [N] working fixes. Private link: mousabatarseh.com/[path]/ — résumé and cover letter are attached.
... B21: Name one strength before the finding. Never send a finding that isn't on the Findings sheet. One follow-up after 7 days. Keep the page noindex; the link is private to the person you send it to. Log the row on Outreach the same day.
